package com.google.analytics.a.a;

import com.google.tagmanager.a.ab;
import com.google.tagmanager.a.ag;
import com.google.tagmanager.a.ah;
import com.google.tagmanager.a.an;
import com.google.tagmanager.a.ao;
import com.google.tagmanager.a.g;
import com.google.tagmanager.a.u;
import java.util.Collections;
import java.util.List;

public final class p extends com.google.tagmanager.a.s
  implements s
{
  public static ao a = new q();
  private static final p c;
  private static volatile an x = null;
  private final g d;
  private int e;
  private ah f;
  private List g;
  private List h;
  private List i;
  private List j;
  private List k;
  private List l;
  private Object m;
  private Object n;
  private Object o;
  private Object p;
  private b q;
  private float r;
  private boolean s;
  private ah t;
  private int u;
  private byte v = -1;
  private int w = -1;

  static
  {
    p localp = new p();
    c = localp;
    localp.C();
  }

  private p()
  {
    this.d = g.a;
  }

  // ERROR //
  private p(com.google.tagmanager.a.j paramj, com.google.tagmanager.a.n paramn)
  {
    // Byte code:
    //   0: aload_0
    //   1: invokespecial 59	com/google/tagmanager/a/s:<init>	()V
    //   4: aload_0
    //   5: bipush 255
    //   7: putfield 61	com/google/analytics/a/a/p:v	B
    //   10: aload_0
    //   11: bipush 255
    //   13: putfield 63	com/google/analytics/a/a/p:w	I
    //   16: aload_0
    //   17: invokespecial 58	com/google/analytics/a/a/p:C	()V
    //   20: iconst_0
    //   21: istore_3
    //   22: invokestatic 77	com/google/tagmanager/a/g:i	()Lcom/google/tagmanager/a/i;
    //   25: astore 4
    //   27: aload 4
    //   29: invokestatic 82	com/google/tagmanager/a/l:a	(Ljava/io/OutputStream;)Lcom/google/tagmanager/a/l;
    //   32: astore 5
    //   34: iconst_0
    //   35: istore 6
    //   37: iload 6
    //   39: ifne +996 -> 1035
    //   42: aload_1
    //   43: invokevirtual 87	com/google/tagmanager/a/j:a	()I
    //   46: istore 14
    //   48: iload 14
    //   50: lookupswitch	default:+146->196, 0:+1230->1280, 10:+165->215, 18:+403->453, 26:+465->515, 34:+508->558, 42:+554->604, 50:+600->650, 58:+646->696, 74:+692->742, 82:+717->767, 98:+742->792, 106:+767->817, 114:+793->843, 125:+867->917, 130:+892->942, 136:+940->990, 144:+963->1013
    //   197: aload_1
    //   198: aload 5
    //   200: aload_2
    //   201: iload 14
    //   203: invokevirtual 90	com/google/analytics/a/a/p:a	(Lcom/google/tagmanager/a/j;Lcom/google/tagmanager/a/l;Lcom/google/tagmanager/a/n;I)Z
    //   206: ifne -169 -> 37
    //   209: iconst_1
    //   210: istore 6
    //   212: goto -175 -> 37
    //   215: aload_1
    //   216: invokevirtual 93	com/google/tagmanager/a/j:g	()Lcom/google/tagmanager/a/g;
    //   219: astore 28
    //   221: iload_3
    //   222: iconst_1
    //   223: iand
    //   224: iconst_1
    //   225: if_icmpeq +18 -> 243
    //   228: aload_0
    //   229: new 95	com/google/tagmanager/a/ag
    //   232: dup
    //   233: invokespecial 96	com/google/tagmanager/a/ag:<init>	()V
    //   236: putfield 98	com/google/analytics/a/a/p:f	Lcom/google/tagmanager/a/ah;
    //   239: iload_3
    //   240: iconst_1
    //   241: ior
    //   242: istore_3
    //   243: aload_0
    //   244: getfield 98	com/google/analytics/a/a/p:f	Lcom/google/tagmanager/a/ah;
    //   247: aload 28
    //   249: invokeinterface 103 2 0
    //   254: goto -217 -> 37
    //   257: astore 13
    //   259: aload 13
    //   261: aload_0
    //   262: invokevirtual 106	com/google/tagmanager/a/ae:a	(Lcom/google/tagmanager/a/ak;)Lcom/google/tagmanager/a/ae;
    //   265: athrow
    //   266: astore 10
    //   268: iload_3
    //   269: iconst_1
    //   270: iand
    //   271: iconst_1
    //   272: if_icmpne +18 -> 290
    //   275: aload_0
    //   276: new 108	com/google/tagmanager/a/bd
    //   279: dup
    //   280: aload_0
    //   281: getfield 98	com/google/analytics/a/a/p:f	Lcom/google/tagmanager/a/ah;
    //   284: invokespecial 111	com/google/tagmanager/a/bd:<init>	(Lcom/google/tagmanager/a/ah;)V
    //   287: putfield 98	com/google/analytics/a/a/p:f	Lcom/google/tagmanager/a/ah;
    //   290: iload_3
    //   291: iconst_2
    //   292: iand
    //   293: iconst_2
    //   294: if_icmpne +14 -> 308
    //   297: aload_0
    //   298: aload_0
    //   299: getfield 113	com/google/analytics/a/a/p:g	Ljava/util/List;
    //   302: invokestatic 119	java/util/Collections:unmodifiableList	(Ljava/util/List;)Ljava/util/List;
    //   305: putfield 113	com/google/analytics/a/a/p:g	Ljava/util/List;
    //   308: iload_3
    //   309: iconst_4
    //   310: iand
    //   311: iconst_4
    //   312: if_icmpne +14 -> 326
    //   315: aload_0
    //   316: aload_0
    //   317: getfield 121	com/google/analytics/a/a/p:h	Ljava/util/List;
    //   320: invokestatic 119	java/util/Collections:unmodifiableList	(Ljava/util/List;)Ljava/util/List;
    //   323: putfield 121	com/google/analytics/a/a/p:h	Ljava/util/List;
    //   326: iload_3
    //   327: bipush 8
    //   329: iand
    //   330: bipush 8
    //   332: if_icmpne +14 -> 346
    //   335: aload_0
    //   336: aload_0
    //   337: getfield 123	com/google/analytics/a/a/p:i	Ljava/util/List;
    //   340: invokestatic 119	java/util/Collections:unmodifiableList	(Ljava/util/List;)Ljava/util/List;
    //   343: putfield 123	com/google/analytics/a/a/p:i	Ljava/util/List;
    //   346: iload_3
    //   347: bipush 16
    //   349: iand
    //   350: bipush 16
    //   352: if_icmpne +14 -> 366
    //   355: aload_0
    //   356: aload_0
    //   357: getfield 125	com/google/analytics/a/a/p:j	Ljava/util/List;
    //   360: invokestatic 119	java/util/Collections:unmodifiableList	(Ljava/util/List;)Ljava/util/List;
    //   363: putfield 125	com/google/analytics/a/a/p:j	Ljava/util/List;
    //   366: iload_3
    //   367: bipush 32
    //   369: iand
    //   370: bipush 32
    //   372: if_icmpne +14 -> 386
    //   375: aload_0
    //   376: aload_0
    //   377: getfield 127	com/google/analytics/a/a/p:k	Ljava/util/List;
    //   380: invokestatic 119	java/util/Collections:unmodifiableList	(Ljava/util/List;)Ljava/util/List;
    //   383: putfield 127	com/google/analytics/a/a/p:k	Ljava/util/List;
    //   386: iload_3
    //   387: bipush 64
    //   389: iand
    //   390: bipush 64
    //   392: if_icmpne +14 -> 406
    //   395: aload_0
    //   396: aload_0
    //   397: getfield 129	com/google/analytics/a/a/p:l	Ljava/util/List;
    //   400: invokestatic 119	java/util/Collections:unmodifiableList	(Ljava/util/List;)Ljava/util/List;
    //   403: putfield 129	com/google/analytics/a/a/p:l	Ljava/util/List;
    //   406: iload_3
    //   407: sipush 16384
    //   410: iand
    //   411: sipush 16384
    //   414: if_icmpne +18 -> 432
    //   417: aload_0
    //   418: new 108	com/google/tagmanager/a/bd
    //   421: dup
    //   422: aload_0
    //   423: getfield 131	com/google/analytics/a/a/p:t	Lcom/google/tagmanager/a/ah;
    //   426: invokespecial 111	com/google/tagmanager/a/bd:<init>	(Lcom/google/tagmanager/a/ah;)V
    //   429: putfield 131	com/google/analytics/a/a/p:t	Lcom/google/tagmanager/a/ah;
    //   432: aload 5
    //   434: invokevirtual 133	com/google/tagmanager/a/l:a	()V
    //   437: aload_0
    //   438: aload 4
    //   440: invokevirtual 137	com/google/tagmanager/a/i:a	()Lcom/google/tagmanager/a/g;
    //   443: putfield 69	com/google/analytics/a/a/p:d	Lcom/google/tagmanager/a/g;
    //   446: aload_0
    //   447: invokevirtual 139	com/google/analytics/a/a/p:t	()V
    //   450: aload 10
    //   452: athrow
    //   453: iload_3
    //   454: iconst_2
    //   455: iand
    //   456: iconst_2
    //   457: if_icmpeq +18 -> 475
    //   460: aload_0
    //   461: new 141	java/util/ArrayList
    //   464: dup
    //   465: invokespecial 142	java/util/ArrayList:<init>	()V
    //   468: putfield 113	com/google/analytics/a/a/p:g	Ljava/util/List;
    //   471: iload_3
    //   472: iconst_2
    //   473: ior
    //   474: istore_3
    //   475: aload_0
    //   476: getfield 113	com/google/analytics/a/a/p:g	Ljava/util/List;
    //   479: aload_1
    //   480: getstatic 145	com/google/analytics/b/a/a/b:a	Lcom/google/tagmanager/a/ao;
    //   483: aload_2
    //   484: invokevirtual 148	com/google/tagmanager/a/j:a	(Lcom/google/tagmanager/a/ao;Lcom/google/tagmanager/a/n;)Lcom/google/tagmanager/a/ak;
    //   487: invokeinterface 154 2 0
    //   492: pop
    //   493: goto -456 -> 37
    //   496: astore 9
    //   498: new 72	com/google/tagmanager/a/ae
    //   501: dup
    //   502: aload 9
    //   504: invokevirtual 158	java/io/IOException:getMessage	()Ljava/lang/String;
    //   507: invokespecial 161	com/google/tagmanager/a/ae:<init>	(Ljava/lang/String;)V
    //   510: aload_0
    //   511: invokevirtual 106	com/google/tagmanager/a/ae:a	(Lcom/google/tagmanager/a/ak;)Lcom/google/tagmanager/a/ae;
    //   514: athrow
    //   515: iload_3
    //   516: iconst_4
    //   517: iand
    //   518: iconst_4
    //   519: if_icmpeq +18 -> 537
    //   522: aload_0
    //   523: new 141	java/util/ArrayList
    //   526: dup
    //   527: invokespecial 142	java/util/ArrayList:<init>	()V
    //   530: putfield 121	com/google/analytics/a/a/p:h	Ljava/util/List;
    //   533: iload_3
    //   534: iconst_4
    //   535: ior
    //   536: istore_3
    //   537: aload_0
    //   538: getfield 121	com/google/analytics/a/a/p:h	Ljava/util/List;
    //   541: aload_1
    //   542: getstatic 164	com/google/analytics/a/a/l:a	Lcom/google/tagmanager/a/ao;
    //   545: aload_2
    //   546: invokevirtual 148	com/google/tagmanager/a/j:a	(Lcom/google/tagmanager/a/ao;Lcom/google/tagmanager/a/n;)Lcom/google/tagmanager/a/ak;
    //   549: invokeinterface 154 2 0
    //   554: pop
    //   555: goto -518 -> 37
    //   558: iload_3
    //   559: bipush 8
    //   561: iand
    //   562: bipush 8
    //   564: if_icmpeq +19 -> 583
    //   567: aload_0
    //   568: new 141	java/util/ArrayList
    //   571: dup
    //   572: invokespecial 142	java/util/ArrayList:<init>	()V
    //   575: putfield 123	com/google/analytics/a/a/p:i	Ljava/util/List;
    //   578: iload_3
    //   579: bipush 8
    //   581: ior
    //   582: istore_3
    //   583: aload_0
    //   584: getfield 123	com/google/analytics/a/a/p:i	Ljava/util/List;
    //   587: aload_1
    //   588: getstatic 167	com/google/analytics/a/a/h:a	Lcom/google/tagmanager/a/ao;
    //   591: aload_2
    //   592: invokevirtual 148	com/google/tagmanager/a/j:a	(Lcom/google/tagmanager/a/ao;Lcom/google/tagmanager/a/n;)Lcom/google/tagmanager/a/ak;
    //   595: invokeinterface 154 2 0
    //   600: pop
    //   601: goto -564 -> 37
    //   604: iload_3
    //   605: bipush 16
    //   607: iand
    //   608: bipush 16
    //   610: if_icmpeq +19 -> 629
    //   613: aload_0
    //   614: new 141	java/util/ArrayList
    //   617: dup
    //   618: invokespecial 142	java/util/ArrayList:<init>	()V
    //   621: putfield 125	com/google/analytics/a/a/p:j	Ljava/util/List;
    //   624: iload_3
    //   625: bipush 16
    //   627: ior
    //   628: istore_3
    //   629: aload_0
    //   630: getfield 125	com/google/analytics/a/a/p:j	Ljava/util/List;
    //   633: aload_1
    //   634: getstatic 167	com/google/analytics/a/a/h:a	Lcom/google/tagmanager/a/ao;
    //   637: aload_2
    //   638: invokevirtual 148	com/google/tagmanager/a/j:a	(Lcom/google/tagmanager/a/ao;Lcom/google/tagmanager/a/n;)Lcom/google/tagmanager/a/ak;
    //   641: invokeinterface 154 2 0
    //   646: pop
    //   647: goto -610 -> 37
    //   650: iload_3
    //   651: bipush 32
    //   653: iand
    //   654: bipush 32
    //   656: if_icmpeq +19 -> 675
    //   659: aload_0
    //   660: new 141	java/util/ArrayList
    //   663: dup
    //   664: invokespecial 142	java/util/ArrayList:<init>	()V
    //   667: putfield 127	com/google/analytics/a/a/p:k	Ljava/util/List;
    //   670: iload_3
    //   671: bipush 32
    //   673: ior
    //   674: istore_3
    //   675: aload_0
    //   676: getfield 127	com/google/analytics/a/a/p:k	Ljava/util/List;
    //   679: aload_1
    //   680: getstatic 167	com/google/analytics/a/a/h:a	Lcom/google/tagmanager/a/ao;
    //   683: aload_2
    //   684: invokevirtual 148	com/google/tagmanager/a/j:a	(Lcom/google/tagmanager/a/ao;Lcom/google/tagmanager/a/n;)Lcom/google/tagmanager/a/ak;
    //   687: invokeinterface 154 2 0
    //   692: pop
    //   693: goto -656 -> 37
    //   696: iload_3
    //   697: bipush 64
    //   699: iand
    //   700: bipush 64
    //   702: if_icmpeq +19 -> 721
    //   705: aload_0
    //   706: new 141	java/util/ArrayList
    //   709: dup
    //   710: invokespecial 142	java/util/ArrayList:<init>	()V
    //   713: putfield 129	com/google/analytics/a/a/p:l	Ljava/util/List;
    //   716: iload_3
    //   717: bipush 64
    //   719: ior
    //   720: istore_3
    //   721: aload_0
    //   722: getfield 129	com/google/analytics/a/a/p:l	Ljava/util/List;
    //   725: aload_1
    //   726: getstatic 170	com/google/analytics/a/a/t:a	Lcom/google/tagmanager/a/ao;
    //   729: aload_2
    //   730: invokevirtual 148	com/google/tagmanager/a/j:a	(Lcom/google/tagmanager/a/ao;Lcom/google/tagmanager/a/n;)Lcom/google/tagmanager/a/ak;
    //   733: invokeinterface 154 2 0
    //   738: pop
    //   739: goto -702 -> 37
    //   742: aload_1
    //   743: invokevirtual 93	com/google/tagmanager/a/j:g	()Lcom/google/tagmanager/a/g;
    //   746: astore 21
    //   748: aload_0
    //   749: iconst_1
    //   750: aload_0
    //   751: getfield 172	com/google/analytics/a/a/p:e	I
    //   754: ior
    //   755: putfield 172	com/google/analytics/a/a/p:e	I
    //   758: aload_0
    //   759: aload 21
    //   761: putfield 174	com/google/analytics/a/a/p:m	Ljava/lang/Object;
    //   764: goto -727 -> 37
    //   767: aload_1
    //   768: invokevirtual 93	com/google/tagmanager/a/j:g	()Lcom/google/tagmanager/a/g;
    //   771: astore 20
    //   773: aload_0
    //   774: iconst_2
    //   775: aload_0
    //   776: getfield 172	com/google/analytics/a/a/p:e	I
    //   779: ior
    //   780: putfield 172	com/google/analytics/a/a/p:e	I
    //   783: aload_0
    //   784: aload 20
    //   786: putfield 176	com/google/analytics/a/a/p:n	Ljava/lang/Object;
    //   789: goto -752 -> 37
    //   792: aload_1
    //   793: invokevirtual 93	com/google/tagmanager/a/j:g	()Lcom/google/tagmanager/a/g;
    //   796: astore 19
    //   798: aload_0
    //   799: iconst_4
    //   800: aload_0
    //   801: getfield 172	com/google/analytics/a/a/p:e	I
    //   804: ior
    //   805: putfield 172	com/google/analytics/a/a/p:e	I
    //   808: aload_0
    //   809: aload 19
    //   811: putfield 178	com/google/analytics/a/a/p:o	Ljava/lang/Object;
    //   814: goto -777 -> 37
    //   817: aload_1
    //   818: invokevirtual 93	com/google/tagmanager/a/j:g	()Lcom/google/tagmanager/a/g;
    //   821: astore 18
    //   823: aload_0
    //   824: bipush 8
    //   826: aload_0
    //   827: getfield 172	com/google/analytics/a/a/p:e	I
    //   830: ior
    //   831: putfield 172	com/google/analytics/a/a/p:e	I
    //   834: aload_0
    //   835: aload 18
    //   837: putfield 180	com/google/analytics/a/a/p:p	Ljava/lang/Object;
    //   840: goto -803 -> 37
    //   843: bipush 16
    //   845: aload_0
    //   846: getfield 172	com/google/analytics/a/a/p:e	I
    //   849: iand
    //   850: bipush 16
    //   852: if_icmpne +422 -> 1274
    //   855: aload_0
    //   856: getfield 182	com/google/analytics/a/a/p:q	Lcom/google/analytics/a/a/b;
    //   859: invokevirtual 187	com/google/analytics/a/a/b:j	()Lcom/google/analytics/a/a/d;
    //   862: astore 16
    //   864: aload_0
    //   865: aload_1
    //   866: getstatic 188	com/google/analytics/a/a/b:a	Lcom/google/tagmanager/a/ao;
    //   869: aload_2
    //   870: invokevirtual 148	com/google/tagmanager/a/j:a	(Lcom/google/tagmanager/a/ao;Lcom/google/tagmanager/a/n;)Lcom/google/tagmanager/a/ak;
    //   873: checkcast 184	com/google/analytics/a/a/b
    //   876: putfield 182	com/google/analytics/a/a/p:q	Lcom/google/analytics/a/a/b;
    //   879: aload 16
    //   881: ifnull +22 -> 903
    //   884: aload 16
    //   886: aload_0
    //   887: getfield 182	com/google/analytics/a/a/p:q	Lcom/google/analytics/a/a/b;
    //   890: invokevirtual 193	com/google/analytics/a/a/d:a	(Lcom/google/analytics/a/a/b;)Lcom/google/analytics/a/a/d;
    //   893: pop
    //   894: aload_0
    //   895: aload 16
    //   897: invokevirtual 196	com/google/analytics/a/a/d:a	()Lcom/google/analytics/a/a/b;
    //   900: putfield 182	com/google/analytics/a/a/p:q	Lcom/google/analytics/a/a/b;
    //   903: aload_0
    //   904: bipush 16
    //   906: aload_0
    //   907: getfield 172	com/google/analytics/a/a/p:e	I
    //   910: ior
    //   911: putfield 172	com/google/analytics/a/a/p:e	I
    //   914: goto -877 -> 37
    //   917: aload_0
    //   918: bipush 32
    //   920: aload_0
    //   921: getfield 172	com/google/analytics/a/a/p:e	I
    //   924: ior
    //   925: putfield 172	com/google/analytics/a/a/p:e	I
    //   928: aload_0
    //   929: aload_1
    //   930: invokevirtual 198	com/google/tagmanager/a/j:k	()I
    //   933: invokestatic 204	java/lang/Float:intBitsToFloat	(I)F
    //   936: putfield 206	com/google/analytics/a/a/p:r	F
    //   939: goto -902 -> 37
    //   942: aload_1
    //   943: invokevirtual 93	com/google/tagmanager/a/j:g	()Lcom/google/tagmanager/a/g;
    //   946: astore 15
    //   948: iload_3
    //   949: sipush 16384
    //   952: iand
    //   953: sipush 16384
    //   956: if_icmpeq +20 -> 976
    //   959: aload_0
    //   960: new 95	com/google/tagmanager/a/ag
    //   963: dup
    //   964: invokespecial 96	com/google/tagmanager/a/ag:<init>	()V
    //   967: putfield 131	com/google/analytics/a/a/p:t	Lcom/google/tagmanager/a/ah;
    //   970: iload_3
    //   971: sipush 16384
    //   974: ior
    //   975: istore_3
    //   976: aload_0
    //   977: getfield 131	com/google/analytics/a/a/p:t	Lcom/google/tagmanager/a/ah;
    //   980: aload 15
    //   982: invokeinterface 103 2 0
    //   987: goto -950 -> 37
    //   990: aload_0
    //   991: sipush 128
    //   994: aload_0
    //   995: getfield 172	com/google/analytics/a/a/p:e	I
    //   998: ior
    //   999: putfield 172	com/google/analytics/a/a/p:e	I
    //   1002: aload_0
    //   1003: aload_1
    //   1004: invokevirtual 208	com/google/tagmanager/a/j:d	()I
    //   1007: putfield 210	com/google/analytics/a/a/p:u	I
    //   1010: goto -973 -> 37
    //   1013: aload_0
    //   1014: bipush 64
    //   1016: aload_0
    //   1017: getfield 172	com/google/analytics/a/a/p:e	I
    //   1020: ior
    //   1021: putfield 172	com/google/analytics/a/a/p:e	I
    //   1024: aload_0
    //   1025: aload_1
    //   1026: invokevirtual 213	com/google/tagmanager/a/j:e	()Z
    //   1029: putfield 215	com/google/analytics/a/a/p:s	Z
    //   1032: goto -995 -> 37
    //   1035: iload_3
    //   1036: iconst_1
    //   1037: iand
    //   1038: iconst_1
    //   1039: if_icmpne +18 -> 1057
    //   1042: aload_0
    //   1043: new 108	com/google/tagmanager/a/bd
    //   1046: dup
    //   1047: aload_0
    //   1048: getfield 98	com/google/analytics/a/a/p:f	Lcom/google/tagmanager/a/ah;
    //   1051: invokespecial 111	com/google/tagmanager/a/bd:<init>	(Lcom/google/tagmanager/a/ah;)V
    //   1054: putfield 98	com/google/analytics/a/a/p:f	Lcom/google/tagmanager/a/ah;
    //   1057: iload_3
    //   1058: iconst_2
    //   1059: iand
    //   1060: iconst_2
    //   1061: if_icmpne +14 -> 1075
    //   1064: aload_0
    //   1065: aload_0
    //   1066: getfield 113	com/google/analytics/a/a/p:g	Ljava/util/List;
    //   1069: invokestatic 119	java/util/Collections:unmodifiableList	(Ljava/util/List;)Ljava/util/List;
    //   1072: putfield 113	com/google/analytics/a/a/p:g	Ljava/util/List;
    //   1075: iload_3
    //   1076: iconst_4
    //   1077: iand
    //   1078: iconst_4
    //   1079: if_icmpne +14 -> 1093
    //   1082: aload_0
    //   1083: aload_0
    //   1084: getfield 121	com/google/analytics/a/a/p:h	Ljava/util/List;
    //   1087: invokestatic 119	java/util/Collections:unmodifiableList	(Ljava/util/List;)Ljava/util/List;
    //   1090: putfield 121	com/google/analytics/a/a/p:h	Ljava/util/List;
    //   1093: iload_3
    //   1094: bipush 8
    //   1096: iand
    //   1097: bipush 8
    //   1099: if_icmpne +14 -> 1113
    //   1102: aload_0
    //   1103: aload_0
    //   1104: getfield 123	com/google/analytics/a/a/p:i	Ljava/util/List;
    //   1107: invokestatic 119	java/util/Collections:unmodifiableList	(Ljava/util/List;)Ljava/util/List;
    //   1110: putfield 123	com/google/analytics/a/a/p:i	Ljava/util/List;
    //   1113: iload_3
    //   1114: bipush 16
    //   1116: iand
    //   1117: bipush 16
    //   1119: if_icmpne +14 -> 1133
    //   1122: aload_0
    //   1123: aload_0
    //   1124: getfield 125	com/google/analytics/a/a/p:j	Ljava/util/List;
    //   1127: invokestatic 119	java/util/Collections:unmodifiableList	(Ljava/util/List;)Ljava/util/List;
    //   1130: putfield 125	com/google/analytics/a/a/p:j	Ljava/util/List;
    //   1133: iload_3
    //   1134: bipush 32
    //   1136: iand
    //   1137: bipush 32
    //   1139: if_icmpne +14 -> 1153
    //   1142: aload_0
    //   1143: aload_0
    //   1144: getfield 127	com/google/analytics/a/a/p:k	Ljava/util/List;
    //   1147: invokestatic 119	java/util/Collections:unmodifiableList	(Ljava/util/List;)Ljava/util/List;
    //   1150: putfield 127	com/google/analytics/a/a/p:k	Ljava/util/List;
    //   1153: iload_3
    //   1154: bipush 64
    //   1156: iand
    //   1157: bipush 64
    //   1159: if_icmpne +14 -> 1173
    //   1162: aload_0
    //   1163: aload_0
    //   1164: getfield 129	com/google/analytics/a/a/p:l	Ljava/util/List;
    //   1167: invokestatic 119	java/util/Collections:unmodifiableList	(Ljava/util/List;)Ljava/util/List;
    //   1170: putfield 129	com/google/analytics/a/a/p:l	Ljava/util/List;
    //   1173: iload_3
    //   1174: sipush 16384
    //   1177: iand
    //   1178: sipush 16384
    //   1181: if_icmpne +18 -> 1199
    //   1184: aload_0
    //   1185: new 108	com/google/tagmanager/a/bd
    //   1188: dup
    //   1189: aload_0
    //   1190: getfield 131	com/google/analytics/a/a/p:t	Lcom/google/tagmanager/a/ah;
    //   1193: invokespecial 111	com/google/tagmanager/a/bd:<init>	(Lcom/google/tagmanager/a/ah;)V
    //   1196: putfield 131	com/google/analytics/a/a/p:t	Lcom/google/tagmanager/a/ah;
    //   1199: aload 5
    //   1201: invokevirtual 133	com/google/tagmanager/a/l:a	()V
    //   1204: aload_0
    //   1205: aload 4
    //   1207: invokevirtual 137	com/google/tagmanager/a/i:a	()Lcom/google/tagmanager/a/g;
    //   1210: putfield 69	com/google/analytics/a/a/p:d	Lcom/google/tagmanager/a/g;
    //   1213: aload_0
    //   1214: invokevirtual 139	com/google/analytics/a/a/p:t	()V
    //   1217: return
    //   1218: astore 8
    //   1220: aload_0
    //   1221: aload 4
    //   1223: invokevirtual 137	com/google/tagmanager/a/i:a	()Lcom/google/tagmanager/a/g;
    //   1226: putfield 69	com/google/analytics/a/a/p:d	Lcom/google/tagmanager/a/g;
    //   1229: goto -16 -> 1213
    //   1232: astore 7
    //   1234: aload_0
    //   1235: aload 4
    //   1237: invokevirtual 137	com/google/tagmanager/a/i:a	()Lcom/google/tagmanager/a/g;
    //   1240: putfield 69	com/google/analytics/a/a/p:d	Lcom/google/tagmanager/a/g;
    //   1243: aload 7
    //   1245: athrow
    //   1246: astore 12
    //   1248: aload_0
    //   1249: aload 4
    //   1251: invokevirtual 137	com/google/tagmanager/a/i:a	()Lcom/google/tagmanager/a/g;
    //   1254: putfield 69	com/google/analytics/a/a/p:d	Lcom/google/tagmanager/a/g;
    //   1257: goto -811 -> 446
    //   1260: astore 11
    //   1262: aload_0
    //   1263: aload 4
    //   1265: invokevirtual 137	com/google/tagmanager/a/i:a	()Lcom/google/tagmanager/a/g;
    //   1268: putfield 69	com/google/analytics/a/a/p:d	Lcom/google/tagmanager/a/g;
    //   1271: aload 11
    //   1273: athrow
    //   1274: aconst_null
    //   1275: astore 16
    //   1277: goto -413 -> 864
    //   1280: iconst_1
    //   1281: istore 6
    //   1283: goto -1246 -> 37
    //
    // Exception table:
    //   from	to	target	type
    //   42	254	257	com/google/tagmanager/a/ae
    //   460	493	257	com/google/tagmanager/a/ae
    //   522	1032	257	com/google/tagmanager/a/ae
    //   42	254	266	finally
    //   259	266	266	finally
    //   460	493	266	finally
    //   498	515	266	finally
    //   522	1032	266	finally
    //   42	254	496	java/io/IOException
    //   460	493	496	java/io/IOException
    //   522	1032	496	java/io/IOException
    //   1199	1204	1218	java/io/IOException
    //   1199	1204	1232	finally
    //   432	437	1246	java/io/IOException
    //   432	437	1260	finally
  }

  private p(u paramu)
  {
    super(0);
    this.d = paramu.h();
  }

  private String A()
  {
    Object localObject1 = this.n;
    if ((localObject1 instanceof String));
    String str;
    for (Object localObject2 = (String)localObject1; ; localObject2 = str)
    {
      return localObject2;
      g localg = (g)localObject1;
      str = localg.f();
      if (!localg.g())
        continue;
      this.n = str;
    }
  }

  private String B()
  {
    Object localObject1 = this.o;
    if ((localObject1 instanceof String));
    String str;
    for (Object localObject2 = (String)localObject1; ; localObject2 = str)
    {
      return localObject2;
      g localg = (g)localObject1;
      str = localg.f();
      if (!localg.g())
        continue;
      this.o = str;
    }
  }

  private void C()
  {
    this.f = ag.a;
    this.g = Collections.emptyList();
    this.h = Collections.emptyList();
    this.i = Collections.emptyList();
    this.j = Collections.emptyList();
    this.k = Collections.emptyList();
    this.l = Collections.emptyList();
    this.m = "";
    this.n = "";
    this.o = "0";
    this.p = "";
    this.q = b.a();
    this.r = 0.0F;
    this.s = false;
    this.t = ag.a;
    this.u = 0;
  }

  public static p a()
  {
    return c;
  }

  private int u()
  {
    return this.g.size();
  }

  private int v()
  {
    return this.h.size();
  }

  private int w()
  {
    return this.i.size();
  }

  private int x()
  {
    return this.j.size();
  }

  private int y()
  {
    return this.k.size();
  }

  private String z()
  {
    Object localObject1 = this.m;
    if ((localObject1 instanceof String));
    String str;
    for (Object localObject2 = (String)localObject1; ; localObject2 = str)
    {
      return localObject2;
      g localg = (g)localObject1;
      str = localg.f();
      if (!localg.g())
        continue;
      this.m = str;
    }
  }

  public final ao b()
  {
    return a;
  }

  public final boolean c()
  {
    int i1 = 1;
    if ((0x1 & this.e) == i1);
    while (true)
    {
      return i1;
      i1 = 0;
    }
  }

  public final boolean d()
  {
    if ((0x2 & this.e) == 2);
    for (int i1 = 1; ; i1 = 0)
      return i1;
  }

  public final boolean e()
  {
    if ((0x4 & this.e) == 4);
    for (int i1 = 1; ; i1 = 0)
      return i1;
  }

  public final boolean equals(Object paramObject)
  {
    boolean bool1 = true;
    if (paramObject == this);
    while (true)
    {
      return bool1;
      if (!(paramObject instanceof p))
      {
        bool1 = super.equals(paramObject);
        continue;
      }
      p localp = (p)paramObject;
      boolean bool2;
      label49: boolean bool3;
      label73: boolean bool4;
      label97: boolean bool5;
      label121: boolean bool6;
      label145: boolean bool7;
      label169: boolean bool8;
      label193: boolean bool9;
      label212: label241: boolean bool10;
      label260: label289: boolean bool11;
      label308: label337: boolean bool12;
      label356: boolean bool13;
      label385: label404: label433: boolean bool14;
      label452: label484: boolean bool15;
      label503: boolean bool16;
      if (this.f.equals(localp.f))
      {
        bool2 = bool1;
        if ((!bool2) || (!this.g.equals(localp.g)))
          break label606;
        bool3 = bool1;
        if ((!bool3) || (!this.h.equals(localp.h)))
          break label612;
        bool4 = bool1;
        if ((!bool4) || (!this.i.equals(localp.i)))
          break label618;
        bool5 = bool1;
        if ((!bool5) || (!this.j.equals(localp.j)))
          break label624;
        bool6 = bool1;
        if ((!bool6) || (!this.k.equals(localp.k)))
          break label630;
        bool7 = bool1;
        if ((!bool7) || (!this.l.equals(localp.l)))
          break label636;
        bool8 = bool1;
        if ((!bool8) || (c() != localp.c()))
          break label642;
        bool9 = bool1;
        if (c())
        {
          if ((!bool9) || (!z().equals(localp.z())))
            break label648;
          bool9 = bool1;
        }
        if ((!bool9) || (d() != localp.d()))
          break label654;
        bool10 = bool1;
        if (d())
        {
          if ((!bool10) || (!A().equals(localp.A())))
            break label660;
          bool10 = bool1;
        }
        if ((!bool10) || (e() != localp.e()))
          break label666;
        bool11 = bool1;
        if (e())
        {
          if ((!bool11) || (!B().equals(localp.B())))
            break label672;
          bool11 = bool1;
        }
        if ((!bool11) || (f() != localp.f()))
          break label678;
        bool12 = bool1;
        if (f())
        {
          if ((!bool12) || (!g().equals(localp.g())))
            break label684;
          bool12 = bool1;
        }
        if ((!bool12) || (h() != localp.h()))
          break label690;
        bool13 = bool1;
        if (h())
        {
          if ((!bool13) || (!this.q.equals(localp.q)))
            break label696;
          bool13 = bool1;
        }
        if ((!bool13) || (n() != localp.n()))
          break label702;
        bool14 = bool1;
        if (n())
        {
          if ((!bool14) || (Float.floatToIntBits(this.r) != Float.floatToIntBits(localp.r)))
            break label708;
          bool14 = bool1;
        }
        if ((!bool14) || (p() != localp.p()))
          break label714;
        bool15 = bool1;
        if (p())
        {
          if ((!bool15) || (this.s != localp.s))
            break label720;
          bool15 = bool1;
        }
        label529: if ((!bool15) || (!this.t.equals(localp.t)))
          break label726;
        bool16 = bool1;
        label553: if ((!bool16) || (r() != localp.r()))
          break label732;
      }
      label642: label648: label654: label660: label666: label672: label678: label684: label690: label696: label702: label708: label714: label720: label726: label732: for (boolean bool17 = bool1; ; bool17 = false)
      {
        if (!r())
          break label738;
        if ((bool17) && (this.u == localp.u))
          break;
        bool1 = false;
        break;
        bool2 = false;
        break label49;
        label606: bool3 = false;
        break label73;
        label612: bool4 = false;
        break label97;
        label618: bool5 = false;
        break label121;
        label624: bool6 = false;
        break label145;
        label630: bool7 = false;
        break label169;
        label636: bool8 = false;
        break label193;
        bool9 = false;
        break label212;
        bool9 = false;
        break label241;
        bool10 = false;
        break label260;
        bool10 = false;
        break label289;
        bool11 = false;
        break label308;
        bool11 = false;
        break label337;
        bool12 = false;
        break label356;
        bool12 = false;
        break label385;
        bool13 = false;
        break label404;
        bool13 = false;
        break label433;
        bool14 = false;
        break label452;
        bool14 = false;
        break label484;
        bool15 = false;
        break label503;
        bool15 = false;
        break label529;
        bool16 = false;
        break label553;
      }
      label738: bool1 = bool17;
    }
  }

  public final boolean f()
  {
    if ((0x8 & this.e) == 8);
    for (int i1 = 1; ; i1 = 0)
      return i1;
  }

  public final String g()
  {
    Object localObject1 = this.p;
    if ((localObject1 instanceof String));
    String str;
    for (Object localObject2 = (String)localObject1; ; localObject2 = str)
    {
      return localObject2;
      g localg = (g)localObject1;
      str = localg.f();
      if (!localg.g())
        continue;
      this.p = str;
    }
  }

  public final boolean h()
  {
    if ((0x10 & this.e) == 16);
    for (int i1 = 1; ; i1 = 0)
      return i1;
  }

  public final int hashCode()
  {
    int i2;
    if (this.b != 0)
      i2 = this.b;
    while (true)
    {
      return i2;
      int i1 = 779 + p.class.hashCode();
      if (this.f.size() > 0)
        i1 = 53 * (1 + i1 * 37) + this.f.hashCode();
      if (u() > 0)
        i1 = 53 * (2 + i1 * 37) + this.g.hashCode();
      if (v() > 0)
        i1 = 53 * (3 + i1 * 37) + this.h.hashCode();
      if (w() > 0)
        i1 = 53 * (4 + i1 * 37) + this.i.hashCode();
      if (x() > 0)
        i1 = 53 * (5 + i1 * 37) + this.j.hashCode();
      if (y() > 0)
        i1 = 53 * (6 + i1 * 37) + this.k.hashCode();
      if (this.l.size() > 0)
        i1 = 53 * (7 + i1 * 37) + this.l.hashCode();
      if (c())
        i1 = 53 * (9 + i1 * 37) + z().hashCode();
      if (d())
        i1 = 53 * (10 + i1 * 37) + A().hashCode();
      if (e())
        i1 = 53 * (12 + i1 * 37) + B().hashCode();
      if (f())
        i1 = 53 * (13 + i1 * 37) + g().hashCode();
      if (h())
        i1 = 53 * (14 + i1 * 37) + this.q.hashCode();
      if (n())
        i1 = 53 * (15 + i1 * 37) + Float.floatToIntBits(this.r);
      if (p())
        i1 = 53 * (18 + i1 * 37) + ab.a(this.s);
      if (this.t.size() > 0)
        i1 = 53 * (16 + i1 * 37) + this.t.hashCode();
      if (r())
        i1 = 53 * (17 + i1 * 37) + this.u;
      i2 = i1 * 29 + this.d.hashCode();
      this.b = i2;
    }
  }

  public final boolean i()
  {
    int i1 = 0;
    int i2 = this.v;
    if (i2 != -1)
      if (i2 == 1)
        i1 = 1;
    while (true)
    {
      return i1;
      for (int i3 = 0; ; i3++)
      {
        if (i3 >= u())
          break label65;
        if (((com.google.analytics.b.a.a.b)this.g.get(i3)).i())
          continue;
        this.v = 0;
        break;
      }
      label65: for (int i4 = 0; ; i4++)
      {
        if (i4 >= v())
          break label111;
        if (((l)this.h.get(i4)).i())
          continue;
        this.v = 0;
        break;
      }
      label111: for (int i5 = 0; ; i5++)
      {
        if (i5 >= w())
          break label157;
        if (((h)this.i.get(i5)).i())
          continue;
        this.v = 0;
        break;
      }
      label157: for (int i6 = 0; ; i6++)
      {
        if (i6 >= x())
          break label203;
        if (((h)this.j.get(i6)).i())
          continue;
        this.v = 0;
        break;
      }
      label203: for (int i7 = 0; ; i7++)
      {
        if (i7 >= y())
          break label249;
        if (((h)this.k.get(i7)).i())
          continue;
        this.v = 0;
        break;
      }
      label249: this.v = 1;
      i1 = 1;
    }
  }

  public final b j()
  {
    return this.q;
  }

  public final boolean n()
  {
    if ((0x20 & this.e) == 32);
    for (int i1 = 1; ; i1 = 0)
      return i1;
  }

  public final float o()
  {
    return this.r;
  }

  public final boolean p()
  {
    if ((0x40 & this.e) == 64);
    for (int i1 = 1; ; i1 = 0)
      return i1;
  }

  public final boolean q()
  {
    return this.s;
  }

  public final boolean r()
  {
    if ((0x80 & this.e) == 128);
    for (int i1 = 1; ; i1 = 0)
      return i1;
  }

  public final int s()
  {
    return this.u;
  }
}

/* Location:           C:\Users\CVN-DAHLIA\AppData\Local\Temp\Rar$EXa0.638\tools\classes-dex2jar.jar
 * Qualified Name:     com.google.analytics.a.a.p
 * JD-Core Version:    0.6.0
 */