package com.google.analytics.a.a;

import com.google.tagmanager.a.an;
import com.google.tagmanager.a.ao;
import com.google.tagmanager.a.g;
import com.google.tagmanager.a.s;
import java.util.Collections;
import java.util.List;

public final class t extends s
  implements w
{
  public static ao a = new u();
  private static final t c;
  private static volatile an q = null;
  private final g d;
  private List e;
  private List f;
  private List g;
  private List h;
  private List i;
  private List j;
  private List k;
  private List l;
  private List m;
  private List n;
  private byte o = -1;
  private int p = -1;

  static
  {
    t localt = new t();
    c = localt;
    localt.c();
  }

  private t()
  {
    this.d = g.a;
  }

  // ERROR //
  private t(com.google.tagmanager.a.j paramj, com.google.tagmanager.a.n paramn)
  {
    // Byte code:
    //   0: aload_0
    //   1: invokespecial 46	com/google/tagmanager/a/s:<init>	()V
    //   4: aload_0
    //   5: bipush 255
    //   7: putfield 48	com/google/analytics/a/a/t:o	B
    //   10: aload_0
    //   11: bipush 255
    //   13: putfield 50	com/google/analytics/a/a/t:p	I
    //   16: aload_0
    //   17: invokespecial 45	com/google/analytics/a/a/t:c	()V
    //   20: invokestatic 64	com/google/tagmanager/a/g:i	()Lcom/google/tagmanager/a/i;
    //   23: astore_3
    //   24: aload_3
    //   25: invokestatic 69	com/google/tagmanager/a/l:a	(Ljava/io/OutputStream;)Lcom/google/tagmanager/a/l;
    //   28: astore 4
    //   30: iconst_0
    //   31: istore 5
    //   33: iconst_0
    //   34: istore 6
    //   36: iload 5
    //   38: ifne +1848 -> 1886
    //   41: aload_1
    //   42: invokevirtual 74	com/google/tagmanager/a/j:a	()I
    //   45: istore 18
    //   47: iload 18
    //   49: lookupswitch	default:+179->228, 0:+2263->2312, 8:+198->247, 10:+247->296, 16:+570->619, 18:+619->668, 24:+720->769, 26:+769->818, 32:+851->900, 34:+903->952, 40:+988->1037, 42:+1040->1089, 48:+1125->1174, 50:+1177->1226, 56:+1262->1311, 58:+1314->1363, 64:+1399->1448, 66:+1454->1503, 72:+1542->1591, 74:+1597->1646, 80:+1685->1734, 82:+1740->1789
    //   229: aload_1
    //   230: aload 4
    //   232: aload_2
    //   233: iload 18
    //   235: invokevirtual 77	com/google/analytics/a/a/t:a	(Lcom/google/tagmanager/a/j;Lcom/google/tagmanager/a/l;Lcom/google/tagmanager/a/n;I)Z
    //   238: ifne -202 -> 36
    //   241: iconst_1
    //   242: istore 5
    //   244: goto -208 -> 36
    //   247: iload 6
    //   249: iconst_1
    //   250: iand
    //   251: iconst_1
    //   252: if_icmpeq +2053 -> 2305
    //   255: aload_0
    //   256: new 79	java/util/ArrayList
    //   259: dup
    //   260: invokespecial 80	java/util/ArrayList:<init>	()V
    //   263: putfield 82	com/google/analytics/a/a/t:e	Ljava/util/List;
    //   266: iload 6
    //   268: iconst_1
    //   269: ior
    //   270: istore 10
    //   272: aload_0
    //   273: getfield 82	com/google/analytics/a/a/t:e	Ljava/util/List;
    //   276: aload_1
    //   277: invokevirtual 84	com/google/tagmanager/a/j:d	()I
    //   280: invokestatic 90	java/lang/Integer:valueOf	(I)Ljava/lang/Integer;
    //   283: invokeinterface 96 2 0
    //   288: pop
    //   289: iload 10
    //   291: istore 6
    //   293: goto -257 -> 36
    //   296: aload_1
    //   297: aload_1
    //   298: invokevirtual 98	com/google/tagmanager/a/j:i	()I
    //   301: invokevirtual 102	com/google/tagmanager/a/j:b	(I)I
    //   304: istore 46
    //   306: iload 6
    //   308: iconst_1
    //   309: iand
    //   310: iconst_1
    //   311: if_icmpeq +1987 -> 2298
    //   314: aload_1
    //   315: invokevirtual 104	com/google/tagmanager/a/j:m	()I
    //   318: ifle +1980 -> 2298
    //   321: aload_0
    //   322: new 79	java/util/ArrayList
    //   325: dup
    //   326: invokespecial 80	java/util/ArrayList:<init>	()V
    //   329: putfield 82	com/google/analytics/a/a/t:e	Ljava/util/List;
    //   332: iload 6
    //   334: iconst_1
    //   335: ior
    //   336: istore 10
    //   338: aload_1
    //   339: invokevirtual 104	com/google/tagmanager/a/j:m	()I
    //   342: ifle +264 -> 606
    //   345: aload_0
    //   346: getfield 82	com/google/analytics/a/a/t:e	Ljava/util/List;
    //   349: aload_1
    //   350: invokevirtual 84	com/google/tagmanager/a/j:d	()I
    //   353: invokestatic 90	java/lang/Integer:valueOf	(I)Ljava/lang/Integer;
    //   356: invokeinterface 96 2 0
    //   361: pop
    //   362: goto -24 -> 338
    //   365: astore 17
    //   367: aload 17
    //   369: aload_0
    //   370: invokevirtual 107	com/google/tagmanager/a/ae:a	(Lcom/google/tagmanager/a/ak;)Lcom/google/tagmanager/a/ae;
    //   373: athrow
    //   374: astore 11
    //   376: iload 10
    //   378: iconst_1
    //   379: iand
    //   380: iconst_1
    //   381: if_icmpne +14 -> 395
    //   384: aload_0
    //   385: aload_0
    //   386: getfield 82	com/google/analytics/a/a/t:e	Ljava/util/List;
    //   389: invokestatic 113	java/util/Collections:unmodifiableList	(Ljava/util/List;)Ljava/util/List;
    //   392: putfield 82	com/google/analytics/a/a/t:e	Ljava/util/List;
    //   395: iload 10
    //   397: iconst_2
    //   398: iand
    //   399: iconst_2
    //   400: if_icmpne +14 -> 414
    //   403: aload_0
    //   404: aload_0
    //   405: getfield 115	com/google/analytics/a/a/t:f	Ljava/util/List;
    //   408: invokestatic 113	java/util/Collections:unmodifiableList	(Ljava/util/List;)Ljava/util/List;
    //   411: putfield 115	com/google/analytics/a/a/t:f	Ljava/util/List;
    //   414: iload 10
    //   416: iconst_4
    //   417: iand
    //   418: iconst_4
    //   419: if_icmpne +14 -> 433
    //   422: aload_0
    //   423: aload_0
    //   424: getfield 117	com/google/analytics/a/a/t:g	Ljava/util/List;
    //   427: invokestatic 113	java/util/Collections:unmodifiableList	(Ljava/util/List;)Ljava/util/List;
    //   430: putfield 117	com/google/analytics/a/a/t:g	Ljava/util/List;
    //   433: iload 10
    //   435: bipush 8
    //   437: iand
    //   438: bipush 8
    //   440: if_icmpne +14 -> 454
    //   443: aload_0
    //   444: aload_0
    //   445: getfield 119	com/google/analytics/a/a/t:h	Ljava/util/List;
    //   448: invokestatic 113	java/util/Collections:unmodifiableList	(Ljava/util/List;)Ljava/util/List;
    //   451: putfield 119	com/google/analytics/a/a/t:h	Ljava/util/List;
    //   454: iload 10
    //   456: bipush 16
    //   458: iand
    //   459: bipush 16
    //   461: if_icmpne +14 -> 475
    //   464: aload_0
    //   465: aload_0
    //   466: getfield 121	com/google/analytics/a/a/t:i	Ljava/util/List;
    //   469: invokestatic 113	java/util/Collections:unmodifiableList	(Ljava/util/List;)Ljava/util/List;
    //   472: putfield 121	com/google/analytics/a/a/t:i	Ljava/util/List;
    //   475: iload 10
    //   477: bipush 32
    //   479: iand
    //   480: bipush 32
    //   482: if_icmpne +14 -> 496
    //   485: aload_0
    //   486: aload_0
    //   487: getfield 123	com/google/analytics/a/a/t:j	Ljava/util/List;
    //   490: invokestatic 113	java/util/Collections:unmodifiableList	(Ljava/util/List;)Ljava/util/List;
    //   493: putfield 123	com/google/analytics/a/a/t:j	Ljava/util/List;
    //   496: iload 10
    //   498: bipush 64
    //   500: iand
    //   501: bipush 64
    //   503: if_icmpne +14 -> 517
    //   506: aload_0
    //   507: aload_0
    //   508: getfield 125	com/google/analytics/a/a/t:k	Ljava/util/List;
    //   511: invokestatic 113	java/util/Collections:unmodifiableList	(Ljava/util/List;)Ljava/util/List;
    //   514: putfield 125	com/google/analytics/a/a/t:k	Ljava/util/List;
    //   517: iload 10
    //   519: sipush 128
    //   522: iand
    //   523: sipush 128
    //   526: if_icmpne +14 -> 540
    //   529: aload_0
    //   530: aload_0
    //   531: getfield 127	com/google/analytics/a/a/t:l	Ljava/util/List;
    //   534: invokestatic 113	java/util/Collections:unmodifiableList	(Ljava/util/List;)Ljava/util/List;
    //   537: putfield 127	com/google/analytics/a/a/t:l	Ljava/util/List;
    //   540: iload 10
    //   542: sipush 256
    //   545: iand
    //   546: sipush 256
    //   549: if_icmpne +14 -> 563
    //   552: aload_0
    //   553: aload_0
    //   554: getfield 129	com/google/analytics/a/a/t:m	Ljava/util/List;
    //   557: invokestatic 113	java/util/Collections:unmodifiableList	(Ljava/util/List;)Ljava/util/List;
    //   560: putfield 129	com/google/analytics/a/a/t:m	Ljava/util/List;
    //   563: iload 10
    //   565: sipush 512
    //   568: iand
    //   569: sipush 512
    //   572: if_icmpne +14 -> 586
    //   575: aload_0
    //   576: aload_0
    //   577: getfield 131	com/google/analytics/a/a/t:n	Ljava/util/List;
    //   580: invokestatic 113	java/util/Collections:unmodifiableList	(Ljava/util/List;)Ljava/util/List;
    //   583: putfield 131	com/google/analytics/a/a/t:n	Ljava/util/List;
    //   586: aload 4
    //   588: invokevirtual 133	com/google/tagmanager/a/l:a	()V
    //   591: aload_0
    //   592: aload_3
    //   593: invokevirtual 138	com/google/tagmanager/a/i:a	()Lcom/google/tagmanager/a/g;
    //   596: putfield 56	com/google/analytics/a/a/t:d	Lcom/google/tagmanager/a/g;
    //   599: aload_0
    //   600: invokevirtual 141	com/google/analytics/a/a/t:t	()V
    //   603: aload 11
    //   605: athrow
    //   606: aload_1
    //   607: iload 46
    //   609: invokevirtual 144	com/google/tagmanager/a/j:c	(I)V
    //   612: iload 10
    //   614: istore 6
    //   616: goto -580 -> 36
    //   619: iload 6
    //   621: iconst_2
    //   622: iand
    //   623: iconst_2
    //   624: if_icmpeq +1667 -> 2291
    //   627: aload_0
    //   628: new 79	java/util/ArrayList
    //   631: dup
    //   632: invokespecial 80	java/util/ArrayList:<init>	()V
    //   635: putfield 115	com/google/analytics/a/a/t:f	Ljava/util/List;
    //   638: iload 6
    //   640: iconst_2
    //   641: ior
    //   642: istore 10
    //   644: aload_0
    //   645: getfield 115	com/google/analytics/a/a/t:f	Ljava/util/List;
    //   648: aload_1
    //   649: invokevirtual 84	com/google/tagmanager/a/j:d	()I
    //   652: invokestatic 90	java/lang/Integer:valueOf	(I)Ljava/lang/Integer;
    //   655: invokeinterface 96 2 0
    //   660: pop
    //   661: iload 10
    //   663: istore 6
    //   665: goto -629 -> 36
    //   668: aload_1
    //   669: aload_1
    //   670: invokevirtual 98	com/google/tagmanager/a/j:i	()I
    //   673: invokevirtual 102	com/google/tagmanager/a/j:b	(I)I
    //   676: istore 43
    //   678: iload 6
    //   680: iconst_2
    //   681: iand
    //   682: iconst_2
    //   683: if_icmpeq +1601 -> 2284
    //   686: aload_1
    //   687: invokevirtual 104	com/google/tagmanager/a/j:m	()I
    //   690: ifle +1594 -> 2284
    //   693: aload_0
    //   694: new 79	java/util/ArrayList
    //   697: dup
    //   698: invokespecial 80	java/util/ArrayList:<init>	()V
    //   701: putfield 115	com/google/analytics/a/a/t:f	Ljava/util/List;
    //   704: iload 6
    //   706: iconst_2
    //   707: ior
    //   708: istore 10
    //   710: aload_1
    //   711: invokevirtual 104	com/google/tagmanager/a/j:m	()I
    //   714: ifle +42 -> 756
    //   717: aload_0
    //   718: getfield 115	com/google/analytics/a/a/t:f	Ljava/util/List;
    //   721: aload_1
    //   722: invokevirtual 84	com/google/tagmanager/a/j:d	()I
    //   725: invokestatic 90	java/lang/Integer:valueOf	(I)Ljava/lang/Integer;
    //   728: invokeinterface 96 2 0
    //   733: pop
    //   734: goto -24 -> 710
    //   737: astore 15
    //   739: new 59	com/google/tagmanager/a/ae
    //   742: dup
    //   743: aload 15
    //   745: invokevirtual 148	java/io/IOException:getMessage	()Ljava/lang/String;
    //   748: invokespecial 151	com/google/tagmanager/a/ae:<init>	(Ljava/lang/String;)V
    //   751: aload_0
    //   752: invokevirtual 107	com/google/tagmanager/a/ae:a	(Lcom/google/tagmanager/a/ak;)Lcom/google/tagmanager/a/ae;
    //   755: athrow
    //   756: aload_1
    //   757: iload 43
    //   759: invokevirtual 144	com/google/tagmanager/a/j:c	(I)V
    //   762: iload 10
    //   764: istore 6
    //   766: goto -730 -> 36
    //   769: iload 6
    //   771: iconst_4
    //   772: iand
    //   773: iconst_4
    //   774: if_icmpeq +1503 -> 2277
    //   777: aload_0
    //   778: new 79	java/util/ArrayList
    //   781: dup
    //   782: invokespecial 80	java/util/ArrayList:<init>	()V
    //   785: putfield 117	com/google/analytics/a/a/t:g	Ljava/util/List;
    //   788: iload 6
    //   790: iconst_4
    //   791: ior
    //   792: istore 10
    //   794: aload_0
    //   795: getfield 117	com/google/analytics/a/a/t:g	Ljava/util/List;
    //   798: aload_1
    //   799: invokevirtual 84	com/google/tagmanager/a/j:d	()I
    //   802: invokestatic 90	java/lang/Integer:valueOf	(I)Ljava/lang/Integer;
    //   805: invokeinterface 96 2 0
    //   810: pop
    //   811: iload 10
    //   813: istore 6
    //   815: goto -779 -> 36
    //   818: aload_1
    //   819: aload_1
    //   820: invokevirtual 98	com/google/tagmanager/a/j:i	()I
    //   823: invokevirtual 102	com/google/tagmanager/a/j:b	(I)I
    //   826: istore 40
    //   828: iload 6
    //   830: iconst_4
    //   831: iand
    //   832: iconst_4
    //   833: if_icmpeq +1437 -> 2270
    //   836: aload_1
    //   837: invokevirtual 104	com/google/tagmanager/a/j:m	()I
    //   840: ifle +1430 -> 2270
    //   843: aload_0
    //   844: new 79	java/util/ArrayList
    //   847: dup
    //   848: invokespecial 80	java/util/ArrayList:<init>	()V
    //   851: putfield 117	com/google/analytics/a/a/t:g	Ljava/util/List;
    //   854: iload 6
    //   856: iconst_4
    //   857: ior
    //   858: istore 10
    //   860: aload_1
    //   861: invokevirtual 104	com/google/tagmanager/a/j:m	()I
    //   864: ifle +23 -> 887
    //   867: aload_0
    //   868: getfield 117	com/google/analytics/a/a/t:g	Ljava/util/List;
    //   871: aload_1
    //   872: invokevirtual 84	com/google/tagmanager/a/j:d	()I
    //   875: invokestatic 90	java/lang/Integer:valueOf	(I)Ljava/lang/Integer;
    //   878: invokeinterface 96 2 0
    //   883: pop
    //   884: goto -24 -> 860
    //   887: aload_1
    //   888: iload 40
    //   890: invokevirtual 144	com/google/tagmanager/a/j:c	(I)V
    //   893: iload 10
    //   895: istore 6
    //   897: goto -861 -> 36
    //   900: iload 6
    //   902: bipush 8
    //   904: iand
    //   905: bipush 8
    //   907: if_icmpeq +1356 -> 2263
    //   910: aload_0
    //   911: new 79	java/util/ArrayList
    //   914: dup
    //   915: invokespecial 80	java/util/ArrayList:<init>	()V
    //   918: putfield 119	com/google/analytics/a/a/t:h	Ljava/util/List;
    //   921: iload 6
    //   923: bipush 8
    //   925: ior
    //   926: istore 10
    //   928: aload_0
    //   929: getfield 119	com/google/analytics/a/a/t:h	Ljava/util/List;
    //   932: aload_1
    //   933: invokevirtual 84	com/google/tagmanager/a/j:d	()I
    //   936: invokestatic 90	java/lang/Integer:valueOf	(I)Ljava/lang/Integer;
    //   939: invokeinterface 96 2 0
    //   944: pop
    //   945: iload 10
    //   947: istore 6
    //   949: goto -913 -> 36
    //   952: aload_1
    //   953: aload_1
    //   954: invokevirtual 98	com/google/tagmanager/a/j:i	()I
    //   957: invokevirtual 102	com/google/tagmanager/a/j:b	(I)I
    //   960: istore 37
    //   962: iload 6
    //   964: bipush 8
    //   966: iand
    //   967: bipush 8
    //   969: if_icmpeq +1287 -> 2256
    //   972: aload_1
    //   973: invokevirtual 104	com/google/tagmanager/a/j:m	()I
    //   976: ifle +1280 -> 2256
    //   979: aload_0
    //   980: new 79	java/util/ArrayList
    //   983: dup
    //   984: invokespecial 80	java/util/ArrayList:<init>	()V
    //   987: putfield 119	com/google/analytics/a/a/t:h	Ljava/util/List;
    //   990: iload 6
    //   992: bipush 8
    //   994: ior
    //   995: istore 10
    //   997: aload_1
    //   998: invokevirtual 104	com/google/tagmanager/a/j:m	()I
    //   1001: ifle +23 -> 1024
    //   1004: aload_0
    //   1005: getfield 119	com/google/analytics/a/a/t:h	Ljava/util/List;
    //   1008: aload_1
    //   1009: invokevirtual 84	com/google/tagmanager/a/j:d	()I
    //   1012: invokestatic 90	java/lang/Integer:valueOf	(I)Ljava/lang/Integer;
    //   1015: invokeinterface 96 2 0
    //   1020: pop
    //   1021: goto -24 -> 997
    //   1024: aload_1
    //   1025: iload 37
    //   1027: invokevirtual 144	com/google/tagmanager/a/j:c	(I)V
    //   1030: iload 10
    //   1032: istore 6
    //   1034: goto -998 -> 36
    //   1037: iload 6
    //   1039: bipush 16
    //   1041: iand
    //   1042: bipush 16
    //   1044: if_icmpeq +1205 -> 2249
    //   1047: aload_0
    //   1048: new 79	java/util/ArrayList
    //   1051: dup
    //   1052: invokespecial 80	java/util/ArrayList:<init>	()V
    //   1055: putfield 121	com/google/analytics/a/a/t:i	Ljava/util/List;
    //   1058: iload 6
    //   1060: bipush 16
    //   1062: ior
    //   1063: istore 10
    //   1065: aload_0
    //   1066: getfield 121	com/google/analytics/a/a/t:i	Ljava/util/List;
    //   1069: aload_1
    //   1070: invokevirtual 84	com/google/tagmanager/a/j:d	()I
    //   1073: invokestatic 90	java/lang/Integer:valueOf	(I)Ljava/lang/Integer;
    //   1076: invokeinterface 96 2 0
    //   1081: pop
    //   1082: iload 10
    //   1084: istore 6
    //   1086: goto -1050 -> 36
    //   1089: aload_1
    //   1090: aload_1
    //   1091: invokevirtual 98	com/google/tagmanager/a/j:i	()I
    //   1094: invokevirtual 102	com/google/tagmanager/a/j:b	(I)I
    //   1097: istore 34
    //   1099: iload 6
    //   1101: bipush 16
    //   1103: iand
    //   1104: bipush 16
    //   1106: if_icmpeq +1136 -> 2242
    //   1109: aload_1
    //   1110: invokevirtual 104	com/google/tagmanager/a/j:m	()I
    //   1113: ifle +1129 -> 2242
    //   1116: aload_0
    //   1117: new 79	java/util/ArrayList
    //   1120: dup
    //   1121: invokespecial 80	java/util/ArrayList:<init>	()V
    //   1124: putfield 121	com/google/analytics/a/a/t:i	Ljava/util/List;
    //   1127: iload 6
    //   1129: bipush 16
    //   1131: ior
    //   1132: istore 10
    //   1134: aload_1
    //   1135: invokevirtual 104	com/google/tagmanager/a/j:m	()I
    //   1138: ifle +23 -> 1161
    //   1141: aload_0
    //   1142: getfield 121	com/google/analytics/a/a/t:i	Ljava/util/List;
    //   1145: aload_1
    //   1146: invokevirtual 84	com/google/tagmanager/a/j:d	()I
    //   1149: invokestatic 90	java/lang/Integer:valueOf	(I)Ljava/lang/Integer;
    //   1152: invokeinterface 96 2 0
    //   1157: pop
    //   1158: goto -24 -> 1134
    //   1161: aload_1
    //   1162: iload 34
    //   1164: invokevirtual 144	com/google/tagmanager/a/j:c	(I)V
    //   1167: iload 10
    //   1169: istore 6
    //   1171: goto -1135 -> 36
    //   1174: iload 6
    //   1176: bipush 32
    //   1178: iand
    //   1179: bipush 32
    //   1181: if_icmpeq +1054 -> 2235
    //   1184: aload_0
    //   1185: new 79	java/util/ArrayList
    //   1188: dup
    //   1189: invokespecial 80	java/util/ArrayList:<init>	()V
    //   1192: putfield 123	com/google/analytics/a/a/t:j	Ljava/util/List;
    //   1195: iload 6
    //   1197: bipush 32
    //   1199: ior
    //   1200: istore 10
    //   1202: aload_0
    //   1203: getfield 123	com/google/analytics/a/a/t:j	Ljava/util/List;
    //   1206: aload_1
    //   1207: invokevirtual 84	com/google/tagmanager/a/j:d	()I
    //   1210: invokestatic 90	java/lang/Integer:valueOf	(I)Ljava/lang/Integer;
    //   1213: invokeinterface 96 2 0
    //   1218: pop
    //   1219: iload 10
    //   1221: istore 6
    //   1223: goto -1187 -> 36
    //   1226: aload_1
    //   1227: aload_1
    //   1228: invokevirtual 98	com/google/tagmanager/a/j:i	()I
    //   1231: invokevirtual 102	com/google/tagmanager/a/j:b	(I)I
    //   1234: istore 31
    //   1236: iload 6
    //   1238: bipush 32
    //   1240: iand
    //   1241: bipush 32
    //   1243: if_icmpeq +985 -> 2228
    //   1246: aload_1
    //   1247: invokevirtual 104	com/google/tagmanager/a/j:m	()I
    //   1250: ifle +978 -> 2228
    //   1253: aload_0
    //   1254: new 79	java/util/ArrayList
    //   1257: dup
    //   1258: invokespecial 80	java/util/ArrayList:<init>	()V
    //   1261: putfield 123	com/google/analytics/a/a/t:j	Ljava/util/List;
    //   1264: iload 6
    //   1266: bipush 32
    //   1268: ior
    //   1269: istore 10
    //   1271: aload_1
    //   1272: invokevirtual 104	com/google/tagmanager/a/j:m	()I
    //   1275: ifle +23 -> 1298
    //   1278: aload_0
    //   1279: getfield 123	com/google/analytics/a/a/t:j	Ljava/util/List;
    //   1282: aload_1
    //   1283: invokevirtual 84	com/google/tagmanager/a/j:d	()I
    //   1286: invokestatic 90	java/lang/Integer:valueOf	(I)Ljava/lang/Integer;
    //   1289: invokeinterface 96 2 0
    //   1294: pop
    //   1295: goto -24 -> 1271
    //   1298: aload_1
    //   1299: iload 31
    //   1301: invokevirtual 144	com/google/tagmanager/a/j:c	(I)V
    //   1304: iload 10
    //   1306: istore 6
    //   1308: goto -1272 -> 36
    //   1311: iload 6
    //   1313: bipush 64
    //   1315: iand
    //   1316: bipush 64
    //   1318: if_icmpeq +903 -> 2221
    //   1321: aload_0
    //   1322: new 79	java/util/ArrayList
    //   1325: dup
    //   1326: invokespecial 80	java/util/ArrayList:<init>	()V
    //   1329: putfield 125	com/google/analytics/a/a/t:k	Ljava/util/List;
    //   1332: iload 6
    //   1334: bipush 64
    //   1336: ior
    //   1337: istore 10
    //   1339: aload_0
    //   1340: getfield 125	com/google/analytics/a/a/t:k	Ljava/util/List;
    //   1343: aload_1
    //   1344: invokevirtual 84	com/google/tagmanager/a/j:d	()I
    //   1347: invokestatic 90	java/lang/Integer:valueOf	(I)Ljava/lang/Integer;
    //   1350: invokeinterface 96 2 0
    //   1355: pop
    //   1356: iload 10
    //   1358: istore 6
    //   1360: goto -1324 -> 36
    //   1363: aload_1
    //   1364: aload_1
    //   1365: invokevirtual 98	com/google/tagmanager/a/j:i	()I
    //   1368: invokevirtual 102	com/google/tagmanager/a/j:b	(I)I
    //   1371: istore 28
    //   1373: iload 6
    //   1375: bipush 64
    //   1377: iand
    //   1378: bipush 64
    //   1380: if_icmpeq +834 -> 2214
    //   1383: aload_1
    //   1384: invokevirtual 104	com/google/tagmanager/a/j:m	()I
    //   1387: ifle +827 -> 2214
    //   1390: aload_0
    //   1391: new 79	java/util/ArrayList
    //   1394: dup
    //   1395: invokespecial 80	java/util/ArrayList:<init>	()V
    //   1398: putfield 125	com/google/analytics/a/a/t:k	Ljava/util/List;
    //   1401: iload 6
    //   1403: bipush 64
    //   1405: ior
    //   1406: istore 10
    //   1408: aload_1
    //   1409: invokevirtual 104	com/google/tagmanager/a/j:m	()I
    //   1412: ifle +23 -> 1435
    //   1415: aload_0
    //   1416: getfield 125	com/google/analytics/a/a/t:k	Ljava/util/List;
    //   1419: aload_1
    //   1420: invokevirtual 84	com/google/tagmanager/a/j:d	()I
    //   1423: invokestatic 90	java/lang/Integer:valueOf	(I)Ljava/lang/Integer;
    //   1426: invokeinterface 96 2 0
    //   1431: pop
    //   1432: goto -24 -> 1408
    //   1435: aload_1
    //   1436: iload 28
    //   1438: invokevirtual 144	com/google/tagmanager/a/j:c	(I)V
    //   1441: iload 10
    //   1443: istore 6
    //   1445: goto -1409 -> 36
    //   1448: iload 6
    //   1450: sipush 128
    //   1453: iand
    //   1454: sipush 128
    //   1457: if_icmpeq +750 -> 2207
    //   1460: aload_0
    //   1461: new 79	java/util/ArrayList
    //   1464: dup
    //   1465: invokespecial 80	java/util/ArrayList:<init>	()V
    //   1468: putfield 127	com/google/analytics/a/a/t:l	Ljava/util/List;
    //   1471: iload 6
    //   1473: sipush 128
    //   1476: ior
    //   1477: istore 10
    //   1479: aload_0
    //   1480: getfield 127	com/google/analytics/a/a/t:l	Ljava/util/List;
    //   1483: aload_1
    //   1484: invokevirtual 84	com/google/tagmanager/a/j:d	()I
    //   1487: invokestatic 90	java/lang/Integer:valueOf	(I)Ljava/lang/Integer;
    //   1490: invokeinterface 96 2 0
    //   1495: pop
    //   1496: iload 10
    //   1498: istore 6
    //   1500: goto -1464 -> 36
    //   1503: aload_1
    //   1504: aload_1
    //   1505: invokevirtual 98	com/google/tagmanager/a/j:i	()I
    //   1508: invokevirtual 102	com/google/tagmanager/a/j:b	(I)I
    //   1511: istore 25
    //   1513: iload 6
    //   1515: sipush 128
    //   1518: iand
    //   1519: sipush 128
    //   1522: if_icmpeq +678 -> 2200
    //   1525: aload_1
    //   1526: invokevirtual 104	com/google/tagmanager/a/j:m	()I
    //   1529: ifle +671 -> 2200
    //   1532: aload_0
    //   1533: new 79	java/util/ArrayList
    //   1536: dup
    //   1537: invokespecial 80	java/util/ArrayList:<init>	()V
    //   1540: putfield 127	com/google/analytics/a/a/t:l	Ljava/util/List;
    //   1543: iload 6
    //   1545: sipush 128
    //   1548: ior
    //   1549: istore 10
    //   1551: aload_1
    //   1552: invokevirtual 104	com/google/tagmanager/a/j:m	()I
    //   1555: ifle +23 -> 1578
    //   1558: aload_0
    //   1559: getfield 127	com/google/analytics/a/a/t:l	Ljava/util/List;
    //   1562: aload_1
    //   1563: invokevirtual 84	com/google/tagmanager/a/j:d	()I
    //   1566: invokestatic 90	java/lang/Integer:valueOf	(I)Ljava/lang/Integer;
    //   1569: invokeinterface 96 2 0
    //   1574: pop
    //   1575: goto -24 -> 1551
    //   1578: aload_1
    //   1579: iload 25
    //   1581: invokevirtual 144	com/google/tagmanager/a/j:c	(I)V
    //   1584: iload 10
    //   1586: istore 6
    //   1588: goto -1552 -> 36
    //   1591: iload 6
    //   1593: sipush 256
    //   1596: iand
    //   1597: sipush 256
    //   1600: if_icmpeq +593 -> 2193
    //   1603: aload_0
    //   1604: new 79	java/util/ArrayList
    //   1607: dup
    //   1608: invokespecial 80	java/util/ArrayList:<init>	()V
    //   1611: putfield 129	com/google/analytics/a/a/t:m	Ljava/util/List;
    //   1614: iload 6
    //   1616: sipush 256
    //   1619: ior
    //   1620: istore 10
    //   1622: aload_0
    //   1623: getfield 129	com/google/analytics/a/a/t:m	Ljava/util/List;
    //   1626: aload_1
    //   1627: invokevirtual 84	com/google/tagmanager/a/j:d	()I
    //   1630: invokestatic 90	java/lang/Integer:valueOf	(I)Ljava/lang/Integer;
    //   1633: invokeinterface 96 2 0
    //   1638: pop
    //   1639: iload 10
    //   1641: istore 6
    //   1643: goto -1607 -> 36
    //   1646: aload_1
    //   1647: aload_1
    //   1648: invokevirtual 98	com/google/tagmanager/a/j:i	()I
    //   1651: invokevirtual 102	com/google/tagmanager/a/j:b	(I)I
    //   1654: istore 22
    //   1656: iload 6
    //   1658: sipush 256
    //   1661: iand
    //   1662: sipush 256
    //   1665: if_icmpeq +521 -> 2186
    //   1668: aload_1
    //   1669: invokevirtual 104	com/google/tagmanager/a/j:m	()I
    //   1672: ifle +514 -> 2186
    //   1675: aload_0
    //   1676: new 79	java/util/ArrayList
    //   1679: dup
    //   1680: invokespecial 80	java/util/ArrayList:<init>	()V
    //   1683: putfield 129	com/google/analytics/a/a/t:m	Ljava/util/List;
    //   1686: iload 6
    //   1688: sipush 256
    //   1691: ior
    //   1692: istore 10
    //   1694: aload_1
    //   1695: invokevirtual 104	com/google/tagmanager/a/j:m	()I
    //   1698: ifle +23 -> 1721
    //   1701: aload_0
    //   1702: getfield 129	com/google/analytics/a/a/t:m	Ljava/util/List;
    //   1705: aload_1
    //   1706: invokevirtual 84	com/google/tagmanager/a/j:d	()I
    //   1709: invokestatic 90	java/lang/Integer:valueOf	(I)Ljava/lang/Integer;
    //   1712: invokeinterface 96 2 0
    //   1717: pop
    //   1718: goto -24 -> 1694
    //   1721: aload_1
    //   1722: iload 22
    //   1724: invokevirtual 144	com/google/tagmanager/a/j:c	(I)V
    //   1727: iload 10
    //   1729: istore 6
    //   1731: goto -1695 -> 36
    //   1734: iload 6
    //   1736: sipush 512
    //   1739: iand
    //   1740: sipush 512
    //   1743: if_icmpeq +436 -> 2179
    //   1746: aload_0
    //   1747: new 79	java/util/ArrayList
    //   1750: dup
    //   1751: invokespecial 80	java/util/ArrayList:<init>	()V
    //   1754: putfield 131	com/google/analytics/a/a/t:n	Ljava/util/List;
    //   1757: iload 6
    //   1759: sipush 512
    //   1762: ior
    //   1763: istore 10
    //   1765: aload_0
    //   1766: getfield 131	com/google/analytics/a/a/t:n	Ljava/util/List;
    //   1769: aload_1
    //   1770: invokevirtual 84	com/google/tagmanager/a/j:d	()I
    //   1773: invokestatic 90	java/lang/Integer:valueOf	(I)Ljava/lang/Integer;
    //   1776: invokeinterface 96 2 0
    //   1781: pop
    //   1782: iload 10
    //   1784: istore 6
    //   1786: goto -1750 -> 36
    //   1789: aload_1
    //   1790: aload_1
    //   1791: invokevirtual 98	com/google/tagmanager/a/j:i	()I
    //   1794: invokevirtual 102	com/google/tagmanager/a/j:b	(I)I
    //   1797: istore 19
    //   1799: iload 6
    //   1801: sipush 512
    //   1804: iand
    //   1805: sipush 512
    //   1808: if_icmpeq +29 -> 1837
    //   1811: aload_1
    //   1812: invokevirtual 104	com/google/tagmanager/a/j:m	()I
    //   1815: ifle +22 -> 1837
    //   1818: aload_0
    //   1819: new 79	java/util/ArrayList
    //   1822: dup
    //   1823: invokespecial 80	java/util/ArrayList:<init>	()V
    //   1826: putfield 131	com/google/analytics/a/a/t:n	Ljava/util/List;
    //   1829: iload 6
    //   1831: sipush 512
    //   1834: ior
    //   1835: istore 6
    //   1837: aload_1
    //   1838: invokevirtual 104	com/google/tagmanager/a/j:m	()I
    //   1841: ifle +23 -> 1864
    //   1844: aload_0
    //   1845: getfield 131	com/google/analytics/a/a/t:n	Ljava/util/List;
    //   1848: aload_1
    //   1849: invokevirtual 84	com/google/tagmanager/a/j:d	()I
    //   1852: invokestatic 90	java/lang/Integer:valueOf	(I)Ljava/lang/Integer;
    //   1855: invokeinterface 96 2 0
    //   1860: pop
    //   1861: goto -24 -> 1837
    //   1864: aload_1
    //   1865: iload 19
    //   1867: invokevirtual 144	com/google/tagmanager/a/j:c	(I)V
    //   1870: goto -1834 -> 36
    //   1873: astore 14
    //   1875: iload 6
    //   1877: istore 10
    //   1879: aload 14
    //   1881: astore 15
    //   1883: goto -1144 -> 739
    //   1886: iload 6
    //   1888: iconst_1
    //   1889: iand
    //   1890: iconst_1
    //   1891: if_icmpne +14 -> 1905
    //   1894: aload_0
    //   1895: aload_0
    //   1896: getfield 82	com/google/analytics/a/a/t:e	Ljava/util/List;
    //   1899: invokestatic 113	java/util/Collections:unmodifiableList	(Ljava/util/List;)Ljava/util/List;
    //   1902: putfield 82	com/google/analytics/a/a/t:e	Ljava/util/List;
    //   1905: iload 6
    //   1907: iconst_2
    //   1908: iand
    //   1909: iconst_2
    //   1910: if_icmpne +14 -> 1924
    //   1913: aload_0
    //   1914: aload_0
    //   1915: getfield 115	com/google/analytics/a/a/t:f	Ljava/util/List;
    //   1918: invokestatic 113	java/util/Collections:unmodifiableList	(Ljava/util/List;)Ljava/util/List;
    //   1921: putfield 115	com/google/analytics/a/a/t:f	Ljava/util/List;
    //   1924: iload 6
    //   1926: iconst_4
    //   1927: iand
    //   1928: iconst_4
    //   1929: if_icmpne +14 -> 1943
    //   1932: aload_0
    //   1933: aload_0
    //   1934: getfield 117	com/google/analytics/a/a/t:g	Ljava/util/List;
    //   1937: invokestatic 113	java/util/Collections:unmodifiableList	(Ljava/util/List;)Ljava/util/List;
    //   1940: putfield 117	com/google/analytics/a/a/t:g	Ljava/util/List;
    //   1943: iload 6
    //   1945: bipush 8
    //   1947: iand
    //   1948: bipush 8
    //   1950: if_icmpne +14 -> 1964
    //   1953: aload_0
    //   1954: aload_0
    //   1955: getfield 119	com/google/analytics/a/a/t:h	Ljava/util/List;
    //   1958: invokestatic 113	java/util/Collections:unmodifiableList	(Ljava/util/List;)Ljava/util/List;
    //   1961: putfield 119	com/google/analytics/a/a/t:h	Ljava/util/List;
    //   1964: iload 6
    //   1966: bipush 16
    //   1968: iand
    //   1969: bipush 16
    //   1971: if_icmpne +14 -> 1985
    //   1974: aload_0
    //   1975: aload_0
    //   1976: getfield 121	com/google/analytics/a/a/t:i	Ljava/util/List;
    //   1979: invokestatic 113	java/util/Collections:unmodifiableList	(Ljava/util/List;)Ljava/util/List;
    //   1982: putfield 121	com/google/analytics/a/a/t:i	Ljava/util/List;
    //   1985: iload 6
    //   1987: bipush 32
    //   1989: iand
    //   1990: bipush 32
    //   1992: if_icmpne +14 -> 2006
    //   1995: aload_0
    //   1996: aload_0
    //   1997: getfield 123	com/google/analytics/a/a/t:j	Ljava/util/List;
    //   2000: invokestatic 113	java/util/Collections:unmodifiableList	(Ljava/util/List;)Ljava/util/List;
    //   2003: putfield 123	com/google/analytics/a/a/t:j	Ljava/util/List;
    //   2006: iload 6
    //   2008: bipush 64
    //   2010: iand
    //   2011: bipush 64
    //   2013: if_icmpne +14 -> 2027
    //   2016: aload_0
    //   2017: aload_0
    //   2018: getfield 125	com/google/analytics/a/a/t:k	Ljava/util/List;
    //   2021: invokestatic 113	java/util/Collections:unmodifiableList	(Ljava/util/List;)Ljava/util/List;
    //   2024: putfield 125	com/google/analytics/a/a/t:k	Ljava/util/List;
    //   2027: iload 6
    //   2029: sipush 128
    //   2032: iand
    //   2033: sipush 128
    //   2036: if_icmpne +14 -> 2050
    //   2039: aload_0
    //   2040: aload_0
    //   2041: getfield 127	com/google/analytics/a/a/t:l	Ljava/util/List;
    //   2044: invokestatic 113	java/util/Collections:unmodifiableList	(Ljava/util/List;)Ljava/util/List;
    //   2047: putfield 127	com/google/analytics/a/a/t:l	Ljava/util/List;
    //   2050: iload 6
    //   2052: sipush 256
    //   2055: iand
    //   2056: sipush 256
    //   2059: if_icmpne +14 -> 2073
    //   2062: aload_0
    //   2063: aload_0
    //   2064: getfield 129	com/google/analytics/a/a/t:m	Ljava/util/List;
    //   2067: invokestatic 113	java/util/Collections:unmodifiableList	(Ljava/util/List;)Ljava/util/List;
    //   2070: putfield 129	com/google/analytics/a/a/t:m	Ljava/util/List;
    //   2073: iload 6
    //   2075: sipush 512
    //   2078: iand
    //   2079: sipush 512
    //   2082: if_icmpne +14 -> 2096
    //   2085: aload_0
    //   2086: aload_0
    //   2087: getfield 131	com/google/analytics/a/a/t:n	Ljava/util/List;
    //   2090: invokestatic 113	java/util/Collections:unmodifiableList	(Ljava/util/List;)Ljava/util/List;
    //   2093: putfield 131	com/google/analytics/a/a/t:n	Ljava/util/List;
    //   2096: aload 4
    //   2098: invokevirtual 133	com/google/tagmanager/a/l:a	()V
    //   2101: aload_0
    //   2102: aload_3
    //   2103: invokevirtual 138	com/google/tagmanager/a/i:a	()Lcom/google/tagmanager/a/g;
    //   2106: putfield 56	com/google/analytics/a/a/t:d	Lcom/google/tagmanager/a/g;
    //   2109: aload_0
    //   2110: invokevirtual 141	com/google/analytics/a/a/t:t	()V
    //   2113: return
    //   2114: astore 8
    //   2116: aload_0
    //   2117: aload_3
    //   2118: invokevirtual 138	com/google/tagmanager/a/i:a	()Lcom/google/tagmanager/a/g;
    //   2121: putfield 56	com/google/analytics/a/a/t:d	Lcom/google/tagmanager/a/g;
    //   2124: goto -15 -> 2109
    //   2127: astore 7
    //   2129: aload_0
    //   2130: aload_3
    //   2131: invokevirtual 138	com/google/tagmanager/a/i:a	()Lcom/google/tagmanager/a/g;
    //   2134: putfield 56	com/google/analytics/a/a/t:d	Lcom/google/tagmanager/a/g;
    //   2137: aload 7
    //   2139: athrow
    //   2140: astore 13
    //   2142: aload_0
    //   2143: aload_3
    //   2144: invokevirtual 138	com/google/tagmanager/a/i:a	()Lcom/google/tagmanager/a/g;
    //   2147: putfield 56	com/google/analytics/a/a/t:d	Lcom/google/tagmanager/a/g;
    //   2150: goto -1551 -> 599
    //   2153: astore 12
    //   2155: aload_0
    //   2156: aload_3
    //   2157: invokevirtual 138	com/google/tagmanager/a/i:a	()Lcom/google/tagmanager/a/g;
    //   2160: putfield 56	com/google/analytics/a/a/t:d	Lcom/google/tagmanager/a/g;
    //   2163: aload 12
    //   2165: athrow
    //   2166: astore 9
    //   2168: iload 6
    //   2170: istore 10
    //   2172: aload 9
    //   2174: astore 11
    //   2176: goto -1800 -> 376
    //   2179: iload 6
    //   2181: istore 10
    //   2183: goto -418 -> 1765
    //   2186: iload 6
    //   2188: istore 10
    //   2190: goto -496 -> 1694
    //   2193: iload 6
    //   2195: istore 10
    //   2197: goto -575 -> 1622
    //   2200: iload 6
    //   2202: istore 10
    //   2204: goto -653 -> 1551
    //   2207: iload 6
    //   2209: istore 10
    //   2211: goto -732 -> 1479
    //   2214: iload 6
    //   2216: istore 10
    //   2218: goto -810 -> 1408
    //   2221: iload 6
    //   2223: istore 10
    //   2225: goto -886 -> 1339
    //   2228: iload 6
    //   2230: istore 10
    //   2232: goto -961 -> 1271
    //   2235: iload 6
    //   2237: istore 10
    //   2239: goto -1037 -> 1202
    //   2242: iload 6
    //   2244: istore 10
    //   2246: goto -1112 -> 1134
    //   2249: iload 6
    //   2251: istore 10
    //   2253: goto -1188 -> 1065
    //   2256: iload 6
    //   2258: istore 10
    //   2260: goto -1263 -> 997
    //   2263: iload 6
    //   2265: istore 10
    //   2267: goto -1339 -> 928
    //   2270: iload 6
    //   2272: istore 10
    //   2274: goto -1414 -> 860
    //   2277: iload 6
    //   2279: istore 10
    //   2281: goto -1487 -> 794
    //   2284: iload 6
    //   2286: istore 10
    //   2288: goto -1578 -> 710
    //   2291: iload 6
    //   2293: istore 10
    //   2295: goto -1651 -> 644
    //   2298: iload 6
    //   2300: istore 10
    //   2302: goto -1964 -> 338
    //   2305: iload 6
    //   2307: istore 10
    //   2309: goto -2037 -> 272
    //   2312: iconst_1
    //   2313: istore 5
    //   2315: goto -2279 -> 36
    //   2318: astore 16
    //   2320: iload 6
    //   2322: istore 10
    //   2324: aload 16
    //   2326: astore 17
    //   2328: goto -1961 -> 367
    //
    // Exception table:
    //   from	to	target	type
    //   272	289	365	com/google/tagmanager/a/ae
    //   338	362	365	com/google/tagmanager/a/ae
    //   606	612	365	com/google/tagmanager/a/ae
    //   644	661	365	com/google/tagmanager/a/ae
    //   710	734	365	com/google/tagmanager/a/ae
    //   756	762	365	com/google/tagmanager/a/ae
    //   794	811	365	com/google/tagmanager/a/ae
    //   860	893	365	com/google/tagmanager/a/ae
    //   928	945	365	com/google/tagmanager/a/ae
    //   997	1030	365	com/google/tagmanager/a/ae
    //   1065	1082	365	com/google/tagmanager/a/ae
    //   1134	1167	365	com/google/tagmanager/a/ae
    //   1202	1219	365	com/google/tagmanager/a/ae
    //   1271	1304	365	com/google/tagmanager/a/ae
    //   1339	1356	365	com/google/tagmanager/a/ae
    //   1408	1441	365	com/google/tagmanager/a/ae
    //   1479	1496	365	com/google/tagmanager/a/ae
    //   1551	1584	365	com/google/tagmanager/a/ae
    //   1622	1639	365	com/google/tagmanager/a/ae
    //   1694	1727	365	com/google/tagmanager/a/ae
    //   1765	1782	365	com/google/tagmanager/a/ae
    //   272	289	374	finally
    //   338	362	374	finally
    //   367	374	374	finally
    //   606	612	374	finally
    //   644	661	374	finally
    //   710	734	374	finally
    //   739	756	374	finally
    //   756	762	374	finally
    //   794	811	374	finally
    //   860	893	374	finally
    //   928	945	374	finally
    //   997	1030	374	finally
    //   1065	1082	374	finally
    //   1134	1167	374	finally
    //   1202	1219	374	finally
    //   1271	1304	374	finally
    //   1339	1356	374	finally
    //   1408	1441	374	finally
    //   1479	1496	374	finally
    //   1551	1584	374	finally
    //   1622	1639	374	finally
    //   1694	1727	374	finally
    //   1765	1782	374	finally
    //   272	289	737	java/io/IOException
    //   338	362	737	java/io/IOException
    //   606	612	737	java/io/IOException
    //   644	661	737	java/io/IOException
    //   710	734	737	java/io/IOException
    //   756	762	737	java/io/IOException
    //   794	811	737	java/io/IOException
    //   860	893	737	java/io/IOException
    //   928	945	737	java/io/IOException
    //   997	1030	737	java/io/IOException
    //   1065	1082	737	java/io/IOException
    //   1134	1167	737	java/io/IOException
    //   1202	1219	737	java/io/IOException
    //   1271	1304	737	java/io/IOException
    //   1339	1356	737	java/io/IOException
    //   1408	1441	737	java/io/IOException
    //   1479	1496	737	java/io/IOException
    //   1551	1584	737	java/io/IOException
    //   1622	1639	737	java/io/IOException
    //   1694	1727	737	java/io/IOException
    //   1765	1782	737	java/io/IOException
    //   41	266	1873	java/io/IOException
    //   296	332	1873	java/io/IOException
    //   627	638	1873	java/io/IOException
    //   668	704	1873	java/io/IOException
    //   777	788	1873	java/io/IOException
    //   818	854	1873	java/io/IOException
    //   910	921	1873	java/io/IOException
    //   952	990	1873	java/io/IOException
    //   1047	1058	1873	java/io/IOException
    //   1089	1127	1873	java/io/IOException
    //   1184	1195	1873	java/io/IOException
    //   1226	1264	1873	java/io/IOException
    //   1321	1332	1873	java/io/IOException
    //   1363	1401	1873	java/io/IOException
    //   1460	1471	1873	java/io/IOException
    //   1503	1543	1873	java/io/IOException
    //   1603	1614	1873	java/io/IOException
    //   1646	1686	1873	java/io/IOException
    //   1746	1757	1873	java/io/IOException
    //   1789	1870	1873	java/io/IOException
    //   2096	2101	2114	java/io/IOException
    //   2096	2101	2127	finally
    //   586	591	2140	java/io/IOException
    //   586	591	2153	finally
    //   41	266	2166	finally
    //   296	332	2166	finally
    //   627	638	2166	finally
    //   668	704	2166	finally
    //   777	788	2166	finally
    //   818	854	2166	finally
    //   910	921	2166	finally
    //   952	990	2166	finally
    //   1047	1058	2166	finally
    //   1089	1127	2166	finally
    //   1184	1195	2166	finally
    //   1226	1264	2166	finally
    //   1321	1332	2166	finally
    //   1363	1401	2166	finally
    //   1460	1471	2166	finally
    //   1503	1543	2166	finally
    //   1603	1614	2166	finally
    //   1646	1686	2166	finally
    //   1746	1757	2166	finally
    //   1789	1870	2166	finally
    //   41	266	2318	com/google/tagmanager/a/ae
    //   296	332	2318	com/google/tagmanager/a/ae
    //   627	638	2318	com/google/tagmanager/a/ae
    //   668	704	2318	com/google/tagmanager/a/ae
    //   777	788	2318	com/google/tagmanager/a/ae
    //   818	854	2318	com/google/tagmanager/a/ae
    //   910	921	2318	com/google/tagmanager/a/ae
    //   952	990	2318	com/google/tagmanager/a/ae
    //   1047	1058	2318	com/google/tagmanager/a/ae
    //   1089	1127	2318	com/google/tagmanager/a/ae
    //   1184	1195	2318	com/google/tagmanager/a/ae
    //   1226	1264	2318	com/google/tagmanager/a/ae
    //   1321	1332	2318	com/google/tagmanager/a/ae
    //   1363	1401	2318	com/google/tagmanager/a/ae
    //   1460	1471	2318	com/google/tagmanager/a/ae
    //   1503	1543	2318	com/google/tagmanager/a/ae
    //   1603	1614	2318	com/google/tagmanager/a/ae
    //   1646	1686	2318	com/google/tagmanager/a/ae
    //   1746	1757	2318	com/google/tagmanager/a/ae
    //   1789	1870	2318	com/google/tagmanager/a/ae
  }

  private t(com.google.tagmanager.a.u paramu)
  {
    super(0);
    this.d = paramu.h();
  }

  public static t a()
  {
    return c;
  }

  private void c()
  {
    this.e = Collections.emptyList();
    this.f = Collections.emptyList();
    this.g = Collections.emptyList();
    this.h = Collections.emptyList();
    this.i = Collections.emptyList();
    this.j = Collections.emptyList();
    this.k = Collections.emptyList();
    this.l = Collections.emptyList();
    this.m = Collections.emptyList();
    this.n = Collections.emptyList();
  }

  public final ao b()
  {
    return a;
  }

  public final boolean equals(Object paramObject)
  {
    boolean bool1 = true;
    if (paramObject == this);
    label49: label309: label315: label319: 
    while (true)
    {
      return bool1;
      if (!(paramObject instanceof t))
      {
        bool1 = super.equals(paramObject);
        continue;
      }
      t localt = (t)paramObject;
      boolean bool2;
      boolean bool3;
      label73: boolean bool4;
      label97: boolean bool5;
      label121: boolean bool6;
      boolean bool7;
      boolean bool8;
      label193: boolean bool9;
      if (this.e.equals(localt.e))
      {
        bool2 = bool1;
        if ((!bool2) || (!this.f.equals(localt.f)))
          break label273;
        bool3 = bool1;
        if ((!bool3) || (!this.g.equals(localt.g)))
          break label279;
        bool4 = bool1;
        if ((!bool4) || (!this.h.equals(localt.h)))
          break label285;
        bool5 = bool1;
        if ((!bool5) || (!this.i.equals(localt.i)))
          break label291;
        bool6 = bool1;
        if ((!bool6) || (!this.j.equals(localt.j)))
          break label297;
        bool7 = bool1;
        if ((!bool7) || (!this.k.equals(localt.k)))
          break label303;
        bool8 = bool1;
        if ((!bool8) || (!this.l.equals(localt.l)))
          break label309;
        bool9 = bool1;
        label217: if ((!bool9) || (!this.m.equals(localt.m)))
          break label315;
      }
      for (boolean bool10 = bool1; ; bool10 = false)
      {
        if ((bool10) && (this.n.equals(localt.n)))
          break label319;
        bool1 = false;
        break;
        bool2 = false;
        break label49;
        bool3 = false;
        break label73;
        bool4 = false;
        break label97;
        bool5 = false;
        break label121;
        bool6 = false;
        break label145;
        bool7 = false;
        break label169;
        bool8 = false;
        break label193;
        bool9 = false;
        break label217;
      }
    }
  }

  public final int hashCode()
  {
    int i2;
    if (this.b != 0)
      i2 = this.b;
    while (true)
    {
      return i2;
      int i1 = 779 + t.class.hashCode();
      if (this.e.size() > 0)
        i1 = 53 * (1 + i1 * 37) + this.e.hashCode();
      if (this.f.size() > 0)
        i1 = 53 * (2 + i1 * 37) + this.f.hashCode();
      if (this.g.size() > 0)
        i1 = 53 * (3 + i1 * 37) + this.g.hashCode();
      if (this.h.size() > 0)
        i1 = 53 * (4 + i1 * 37) + this.h.hashCode();
      if (this.i.size() > 0)
        i1 = 53 * (5 + i1 * 37) + this.i.hashCode();
      if (this.j.size() > 0)
        i1 = 53 * (6 + i1 * 37) + this.j.hashCode();
      if (this.k.size() > 0)
        i1 = 53 * (7 + i1 * 37) + this.k.hashCode();
      if (this.l.size() > 0)
        i1 = 53 * (8 + i1 * 37) + this.l.hashCode();
      if (this.m.size() > 0)
        i1 = 53 * (9 + i1 * 37) + this.m.hashCode();
      if (this.n.size() > 0)
        i1 = 53 * (10 + i1 * 37) + this.n.hashCode();
      i2 = i1 * 29 + this.d.hashCode();
      this.b = i2;
    }
  }

  public final boolean i()
  {
    byte b = 1;
    int i1 = this.o;
    if (i1 != -1)
      if (i1 != b);
    while (true)
    {
      return b;
      b = 0;
      continue;
      this.o = b;
    }
  }
}

/* Location:           C:\Users\CVN-DAHLIA\AppData\Local\Temp\Rar$EXa0.638\tools\classes-dex2jar.jar
 * Qualified Name:     com.google.analytics.a.a.t
 * JD-Core Version:    0.6.0
 */