package com.antispycell.connmonitor;

import android.os.AsyncTask;
import android.widget.TextView;

public final class bc extends AsyncTask
{
  private TextView b;
  private TextView c;
  private String d = null;
  private String e = null;
  private String f = null;

  public bc(IPDetails paramIPDetails, TextView paramTextView1, TextView paramTextView2, String paramString)
  {
    this.f = paramString;
    this.b = paramTextView1;
    this.c = paramTextView2;
  }

  // ERROR //
  private java.lang.Boolean a()
  {
    // Byte code:
    //   0: new 37	java/net/Socket
    //   3: dup
    //   4: ldc 39
    //   6: bipush 43
    //   8: invokespecial 42	java/net/Socket:<init>	(Ljava/lang/String;I)V
    //   11: astore_1
    //   12: aload_1
    //   13: invokevirtual 46	java/net/Socket:getInputStream	()Ljava/io/InputStream;
    //   16: astore 10
    //   18: aload_1
    //   19: invokevirtual 50	java/net/Socket:getOutputStream	()Ljava/io/OutputStream;
    //   22: astore 11
    //   24: aload_0
    //   25: new 52	java/lang/StringBuilder
    //   28: dup
    //   29: aload_0
    //   30: getfield 26	com/antispycell/connmonitor/bc:f	Ljava/lang/String;
    //   33: invokestatic 58	java/lang/String:valueOf	(Ljava/lang/Object;)Ljava/lang/String;
    //   36: invokespecial 61	java/lang/StringBuilder:<init>	(Ljava/lang/String;)V
    //   39: ldc 63
    //   41: invokevirtual 67	java/lang/StringBuilder:append	(Ljava/lang/String;)Ljava/lang/StringBuilder;
    //   44: invokevirtual 71	java/lang/StringBuilder:toString	()Ljava/lang/String;
    //   47: putfield 26	com/antispycell/connmonitor/bc:f	Ljava/lang/String;
    //   50: aload 11
    //   52: aload_0
    //   53: getfield 26	com/antispycell/connmonitor/bc:f	Ljava/lang/String;
    //   56: invokevirtual 75	java/lang/String:getBytes	()[B
    //   59: invokevirtual 81	java/io/OutputStream:write	([B)V
    //   62: aconst_null
    //   63: astore_3
    //   64: aload 10
    //   66: invokevirtual 87	java/io/InputStream:read	()I
    //   69: istore 12
    //   71: iload 12
    //   73: bipush 255
    //   75: if_icmpne +83 -> 158
    //   78: aload_1
    //   79: invokevirtual 90	java/net/Socket:close	()V
    //   82: aload_3
    //   83: ifnull +371 -> 454
    //   86: aload_3
    //   87: invokevirtual 93	java/lang/String:length	()I
    //   90: sipush 200
    //   93: if_icmple +361 -> 454
    //   96: aload_3
    //   97: ldc 95
    //   99: invokevirtual 99	java/lang/String:split	(Ljava/lang/String;)[Ljava/lang/String;
    //   102: astore 7
    //   104: aconst_null
    //   105: astore 4
    //   107: aconst_null
    //   108: astore 6
    //   110: iconst_0
    //   111: istore 8
    //   113: aconst_null
    //   114: astore 5
    //   116: iload 8
    //   118: aload 7
    //   120: arraylength
    //   121: if_icmplt +87 -> 208
    //   124: aload_0
    //   125: new 52	java/lang/StringBuilder
    //   128: dup
    //   129: aload 6
    //   131: invokestatic 58	java/lang/String:valueOf	(Ljava/lang/Object;)Ljava/lang/String;
    //   134: invokespecial 61	java/lang/StringBuilder:<init>	(Ljava/lang/String;)V
    //   137: aload 4
    //   139: invokevirtual 67	java/lang/StringBuilder:append	(Ljava/lang/String;)Ljava/lang/StringBuilder;
    //   142: aload 5
    //   144: invokevirtual 67	java/lang/StringBuilder:append	(Ljava/lang/String;)Ljava/lang/StringBuilder;
    //   147: invokevirtual 71	java/lang/StringBuilder:toString	()Ljava/lang/String;
    //   150: putfield 24	com/antispycell/connmonitor/bc:e	Ljava/lang/String;
    //   153: iconst_1
    //   154: invokestatic 104	java/lang/Boolean:valueOf	(Z)Ljava/lang/Boolean;
    //   157: areturn
    //   158: new 52	java/lang/StringBuilder
    //   161: dup
    //   162: aload_3
    //   163: invokestatic 58	java/lang/String:valueOf	(Ljava/lang/Object;)Ljava/lang/String;
    //   166: invokespecial 61	java/lang/StringBuilder:<init>	(Ljava/lang/String;)V
    //   169: iload 12
    //   171: i2c
    //   172: invokevirtual 107	java/lang/StringBuilder:append	(C)Ljava/lang/StringBuilder;
    //   175: invokevirtual 71	java/lang/StringBuilder:toString	()Ljava/lang/String;
    //   178: astore 13
    //   180: aload 13
    //   182: astore_3
    //   183: goto -119 -> 64
    //   186: astore 9
    //   188: aconst_null
    //   189: astore_3
    //   190: aload 9
    //   192: invokevirtual 110	java/net/UnknownHostException:printStackTrace	()V
    //   195: goto -113 -> 82
    //   198: astore_2
    //   199: aconst_null
    //   200: astore_3
    //   201: aload_2
    //   202: invokevirtual 111	java/io/IOException:printStackTrace	()V
    //   205: goto -123 -> 82
    //   208: aload 7
    //   210: iload 8
    //   212: aaload
    //   213: ifnull +43 -> 256
    //   216: aload 7
    //   218: iload 8
    //   220: aaload
    //   221: ldc 113
    //   223: invokevirtual 117	java/lang/String:startsWith	(Ljava/lang/String;)Z
    //   226: ifeq +30 -> 256
    //   229: aload_0
    //   230: aload 7
    //   232: iload 8
    //   234: aaload
    //   235: iconst_1
    //   236: aload 7
    //   238: iload 8
    //   240: aaload
    //   241: ldc 119
    //   243: invokevirtual 123	java/lang/String:indexOf	(Ljava/lang/String;)I
    //   246: iadd
    //   247: invokevirtual 127	java/lang/String:substring	(I)Ljava/lang/String;
    //   250: invokevirtual 130	java/lang/String:trim	()Ljava/lang/String;
    //   253: putfield 22	com/antispycell/connmonitor/bc:d	Ljava/lang/String;
    //   256: aload 7
    //   258: iload 8
    //   260: aaload
    //   261: ifnull +59 -> 320
    //   264: aload 7
    //   266: iload 8
    //   268: aaload
    //   269: ldc 132
    //   271: invokevirtual 117	java/lang/String:startsWith	(Ljava/lang/String;)Z
    //   274: ifeq +46 -> 320
    //   277: new 52	java/lang/StringBuilder
    //   280: dup
    //   281: aload 7
    //   283: iload 8
    //   285: aaload
    //   286: iconst_1
    //   287: aload 7
    //   289: iload 8
    //   291: aaload
    //   292: ldc 119
    //   294: invokevirtual 123	java/lang/String:indexOf	(Ljava/lang/String;)I
    //   297: iadd
    //   298: invokevirtual 127	java/lang/String:substring	(I)Ljava/lang/String;
    //   301: invokevirtual 130	java/lang/String:trim	()Ljava/lang/String;
    //   304: invokestatic 58	java/lang/String:valueOf	(Ljava/lang/Object;)Ljava/lang/String;
    //   307: invokespecial 61	java/lang/StringBuilder:<init>	(Ljava/lang/String;)V
    //   310: ldc 63
    //   312: invokevirtual 67	java/lang/StringBuilder:append	(Ljava/lang/String;)Ljava/lang/StringBuilder;
    //   315: invokevirtual 71	java/lang/StringBuilder:toString	()Ljava/lang/String;
    //   318: astore 6
    //   320: aload 7
    //   322: iload 8
    //   324: aaload
    //   325: ifnull +59 -> 384
    //   328: aload 7
    //   330: iload 8
    //   332: aaload
    //   333: ldc 134
    //   335: invokevirtual 117	java/lang/String:startsWith	(Ljava/lang/String;)Z
    //   338: ifeq +46 -> 384
    //   341: new 52	java/lang/StringBuilder
    //   344: dup
    //   345: aload 7
    //   347: iload 8
    //   349: aaload
    //   350: iconst_1
    //   351: aload 7
    //   353: iload 8
    //   355: aaload
    //   356: ldc 119
    //   358: invokevirtual 123	java/lang/String:indexOf	(Ljava/lang/String;)I
    //   361: iadd
    //   362: invokevirtual 127	java/lang/String:substring	(I)Ljava/lang/String;
    //   365: invokevirtual 130	java/lang/String:trim	()Ljava/lang/String;
    //   368: invokestatic 58	java/lang/String:valueOf	(Ljava/lang/Object;)Ljava/lang/String;
    //   371: invokespecial 61	java/lang/StringBuilder:<init>	(Ljava/lang/String;)V
    //   374: ldc 63
    //   376: invokevirtual 67	java/lang/StringBuilder:append	(Ljava/lang/String;)Ljava/lang/StringBuilder;
    //   379: invokevirtual 71	java/lang/StringBuilder:toString	()Ljava/lang/String;
    //   382: astore 4
    //   384: aload 7
    //   386: iload 8
    //   388: aaload
    //   389: ifnull +59 -> 448
    //   392: aload 7
    //   394: iload 8
    //   396: aaload
    //   397: ldc 136
    //   399: invokevirtual 117	java/lang/String:startsWith	(Ljava/lang/String;)Z
    //   402: ifeq +46 -> 448
    //   405: new 52	java/lang/StringBuilder
    //   408: dup
    //   409: aload 7
    //   411: iload 8
    //   413: aaload
    //   414: iconst_1
    //   415: aload 7
    //   417: iload 8
    //   419: aaload
    //   420: ldc 119
    //   422: invokevirtual 123	java/lang/String:indexOf	(Ljava/lang/String;)I
    //   425: iadd
    //   426: invokevirtual 127	java/lang/String:substring	(I)Ljava/lang/String;
    //   429: invokevirtual 130	java/lang/String:trim	()Ljava/lang/String;
    //   432: invokestatic 58	java/lang/String:valueOf	(Ljava/lang/Object;)Ljava/lang/String;
    //   435: invokespecial 61	java/lang/StringBuilder:<init>	(Ljava/lang/String;)V
    //   438: ldc 63
    //   440: invokevirtual 67	java/lang/StringBuilder:append	(Ljava/lang/String;)Ljava/lang/StringBuilder;
    //   443: invokevirtual 71	java/lang/StringBuilder:toString	()Ljava/lang/String;
    //   446: astore 5
    //   448: iinc 8 1
    //   451: goto -335 -> 116
    //   454: ldc 138
    //   456: astore 4
    //   458: aload 4
    //   460: astore 5
    //   462: aload 4
    //   464: astore 6
    //   466: goto -342 -> 124
    //   469: astore_2
    //   470: goto -269 -> 201
    //   473: astore 9
    //   475: goto -285 -> 190
    //
    // Exception table:
    //   from	to	target	type
    //   0	62	186	java/net/UnknownHostException
    //   0	62	198	java/io/IOException
    //   64	82	469	java/io/IOException
    //   158	180	469	java/io/IOException
    //   64	82	473	java/net/UnknownHostException
    //   158	180	473	java/net/UnknownHostException
  }
}

/* Location:           C:\Users\CVN-DAHLIA\AppData\Local\Temp\Rar$EXa0.638\tools\classes-dex2jar.jar
 * Qualified Name:     com.antispycell.connmonitor.bc
 * JD-Core Version:    0.6.0
 */